{"leaderboards":[{"_links":{"item":{"href":"/leaderboard/08/1AE1A7D894960B38E09E7494373378D87305A163/04.json"}},"name":"Luigi Circuit","authors":["Nintendo"],"slotId":8,"correctSlotId":8,"inCtgp":true,"defaultTrack":true,"200cc":true,"categoryId":4,"trackId":"1AE1A7D894960B38E09E7494373378D87305A163","ghostCount":61673,"uniquePlayers":21446,"popularity":110,"lastChanged":"2024-10-26T19:45:56Z","fastestTime":"00:46.258143377125","fastestTimeSimple":"00:46.259","fastestTimeLastChange":"2023-05-17T21:27:54Z"},{"_links":{"item":{"href":"/leaderboard/01/90720A7D57A7C76E2347782F6BDE5D22342FB7DD/04.json"}},"name":"Moo Moo Meadows","authors":["Nintendo"],"slotId":1,"correctSlotId":1,"inCtgp":true,"defaultTrack":true,"200cc":true,"categoryId":4,"trackId":"90720A7D57A7C76E2347782F6BDE5D22342FB7DD","ghostCount":15910,"uniquePlayers":7081,"popularity":33,"lastChanged":"2024-10-26T15:09:27Z","fastestTime":"00:51.051728884220","fastestTimeSimple":"00:51.052","fastestTimeLastChange":"2023-05-16T04:55:19Z"},{"_links":{"item":{"href":"/leaderboard/02/0E380357AFFCFD8722329994885699D9927F8276/04.json"}},"name":"Mushroom Gorge","authors":["Nintendo"],"slotId":2,"correctSlotId":2,"inCtgp":true,"defaultTrack":true,"200cc":true,"categoryId":4,"trackId":"0E380357AFFCFD8722329994885699D9927F8276","ghostCount":969,"uniquePlayers":626,"popularity":4,"lastChanged":"2024-10-24T17:48:32Z","fastestTime":"01:14.918521849453","fastestTimeSimple":"01:14.919","fastestTimeLastChange":"2024-05-03T21:44:31Z"},{"_links":{"item":{"href":"/leaderboard/02/0E380357AFFCFD8722329994885699D9927F8276/05.json"}},"name":"Mushroom Gorge","authors":["Nintendo"],"slotId":2,"correctSlotId":2,"inCtgp":true,"defaultTrack":true,"200cc":true,"categoryId":5,"trackId":"0E380357AFFCFD8722329994885699D9927F8276","ghostCount":2106,"uniquePlayers":922,"popularity":13,"lastChanged":"2024-10-16T19:06:44Z","fastestTime":"00:24.261116594374","fastestTimeSimple":"00:24.262","fastestTimeLastChange":"2019-07-18T18:46:14Z"},{"_links":{"item":{"href":"/leaderboard/02/0E380357AFFCFD8722329994885699D9927F8276/06.json"}},"name":"Mushroom Gorge","authors":["Nintendo"],"slotId":2,"correctSlotId":2,"inCtgp":true,"defaultTrack":true,"200cc":true,"categoryId":6,"trackId":"0E380357AFFCFD8722329994885699D9927F8276","ghostCount":27795,"uniquePlayers":9784,"popularity":49,"lastChanged":"2024-10-26T01:46:01Z","fastestTime":"01:12.847800728664","fastestTimeSimple":"01:12.848","fastestTimeLastChange":"2024-02-16T01:22:17Z"},{"_links":{"item":{"href":"/leaderboard/04/1896AEA49617A571C66FF778D8F2ABBE9E5D7479/04.json"}},"name":"Toad's Factory","authors":["Nintendo"],"slotId":4,"correctSlotId":4,"inCtgp":true,"defaultTrack":true,"200cc":true,"categoryId":4,"trackId":"1896AEA49617A571C66FF778D8F2ABBE9E5D7479","ghostCount":342,"uniquePlayers":199,"popularity":0,"lastChanged":"2024-03-07T17:03:21Z","fastestTime":"01:15.027827442288","fastestTimeSimple":"01:15.028","fastestTimeLastChange":"2024-03-01T15:22:54Z"},{"_links":{"item":{"href":"/leaderboard/04/1896AEA49617A571C66FF778D8F2ABBE9E5D7479/06.json"}},"name":"Toad's Factory","authors":["Nintendo"],"slotId":4,"correctSlotId":4,"inCtgp":true,"defaultTrack":true,"200cc":true,"categoryId":6,"trackId":"1896AEA49617A571C66FF778D8F2ABBE9E5D7479","ghostCount":17322,"uniquePlayers":7992,"popularity":39,"lastChanged":"2024-10-25T20:18:47Z","fastestTime":"01:15.870158384144","fastestTimeSimple":"01:15.871","fastestTimeLastChange":"2024-05-11T11:42:56Z"},{"_links":{"item":{"href":"/leaderboard/00/7752BB51EDBC4A95377C0A05B0E0DA1503786625/04.json"}},"name":"Mario Circuit","authors":["Nintendo"],"slotId":0,"correctSlotId":0,"inCtgp":true,"defaultTrack":true,"200cc":true,"categoryId":4,"trackId":"7752BB51EDBC4A95377C0A05B0E0DA1503786625","ghostCount":16967,"uniquePlayers":6452,"popularity":44,"lastChanged":"2024-10-26T15:09:27Z","fastestTime":"00:53.671115733862","fastestTimeSimple":"00:53.672","fastestTimeLastChange":"2024-05-10T16:05:45Z"},{"_links":{"item":{"href":"/leaderboard/00/7752BB51EDBC4A95377C0A05B0E0DA1503786625/05.json"}},"name":"Mario Circuit","authors":["Nintendo"],"slotId":0,"correctSlotId":0,"inCtgp":true,"defaultTrack":true,"200cc":true,"categoryId":5,"trackId":"7752BB51EDBC4A95377C0A05B0E0DA1503786625","ghostCount":3243,"uniquePlayers":1044,"popularity":5,"lastChanged":"2024-10-25T14:09:47Z","fastestTime":"00:39.384495579243","fastestTimeSimple":"00:39.385","fastestTimeLastChange":"2023-06-08T01:56:39Z"},{"_links":{"item":{"href":"/leaderboard/05/E4BF364CB0C5899907585D731621CA930A4EF85C/04.json"}},"name":"Coconut Mall","authors":["Nintendo"],"slotId":5,"correctSlotId":5,"inCtgp":true,"defaultTrack":true,"200cc":true,"categoryId":4,"trackId":"E4BF364CB0C5899907585D731621CA930A4EF85C","ghostCount":7798,"uniquePlayers":2637,"popularity":16,"lastChanged":"2024-10-25T19:55:59Z","fastestTime":"01:05.008784042493","fastestTimeSimple":"01:05.009","fastestTimeLastChange":"2024-08-05T23:08:51Z"},{"_links":{"item":{"href":"/leaderboard/05/E4BF364CB0C5899907585D731621CA930A4EF85C/05.json"}},"name":"Coconut Mall","authors":["Nintendo"],"slotId":5,"correctSlotId":5,"inCtgp":true,"defaultTrack":true,"200cc":true,"categoryId":5,"trackId":"E4BF364CB0C5899907585D731621CA930A4EF85C","ghostCount":4564,"uniquePlayers":1389,"popularity":9,"lastChanged":"2024-10-24T18:13:53Z","fastestTime":"00:27.376287903309","fastestTimeSimple":"00:27.377","fastestTimeLastChange":"2023-04-20T19:17:46Z"},{"_links":{"item":{"href":"/leaderboard/05/E4BF364CB0C5899907585D731621CA930A4EF85C/06.json"}},"name":"Coconut Mall","authors":["Nintendo"],"slotId":5,"correctSlotId":5,"inCtgp":true,"defaultTrack":true,"200cc":true,"categoryId":6,"trackId":"E4BF364CB0C5899907585D731621CA930A4EF85C","ghostCount":12715,"uniquePlayers":6460,"popularity":21,"lastChanged":"2024-10-24T18:13:53Z","fastestTime":"01:14.620494287670","fastestTimeSimple":"01:14.621","fastestTimeLastChange":"2020-01-02T23:03:55Z"},{"_links":{"item":{"href":"/leaderboard/06/B02ED72E00B400647BDA6845BE387C47D251F9D1/04.json"}},"name":"DK Summit","authors":["Nintendo"],"slotId":6,"correctSlotId":6,"inCtgp":true,"defaultTrack":true,"200cc":true,"trackId":"B02ED72E00B400647BDA6845BE387C47D251F9D1","ghostCount":15779,"uniquePlayers":7329,"popularity":46,"lastChanged":"2024-10-26T14:22:25Z","fastestTime":"01:12.465710474372","fastestTimeSimple":"01:12.466","fastestTimeLastChange":"2024-05-07T16:39:08Z"},{"_links":{"item":{"href":"/leaderboard/07/D1A453B43D6920A78565E65A4597E353B177ABD0/04.json"}},"name":"Wario's Gold Mine","authors":["Nintendo"],"slotId":7,"correctSlotId":7,"inCtgp":true,"defaultTrack":true,"200cc":true,"categoryId":4,"trackId":"D1A453B43D6920A78565E65A4597E353B177ABD0","ghostCount":2852,"uniquePlayers":1710,"popularity":10,"lastChanged":"2024-10-21T20:33:04Z","fastestTime":"01:14.552264887810","fastestTimeSimple":"01:14.553","fastestTimeLastChange":"2023-01-22T23:07:16Z"},{"_links":{"item":{"href":"/leaderboard/07/D1A453B43D6920A78565E65A4597E353B177ABD0/05.json"}},"name":"Wario's Gold Mine","authors":["Nintendo"],"slotId":7,"correctSlotId":7,"inCtgp":true,"defaultTrack":true,"200cc":true,"categoryId":5,"trackId":"D1A453B43D6920A78565E65A4597E353B177ABD0","ghostCount":6018,"uniquePlayers":2122,"popularity":15,"lastChanged":"2024-10-25T00:55:41Z","fastestTime":"00:28.366780926630","fastestTimeSimple":"00:28.367","fastestTimeLastChange":"2024-04-26T01:06:34Z"},{"_links":{"item":{"href":"/leaderboard/09/72D0241C75BE4A5EBD242B9D8D89B1D6FD56BE8F/04.json"}},"name":"Daisy Circuit","authors":["Nintendo"],"slotId":9,"correctSlotId":9,"inCtgp":true,"defaultTrack":true,"200cc":true,"categoryId":4,"trackId":"72D0241C75BE4A5EBD242B9D8D89B1D6FD56BE8F","ghostCount":7571,"uniquePlayers":3797,"popularity":11,"lastChanged":"2024-10-21T22:22:16Z","fastestTime":"01:02.002547909260","fastestTimeSimple":"01:02.003","fastestTimeLastChange":"2024-08-08T21:04:50Z"},{"_links":{"item":{"href":"/leaderboard/0F/52F01AE3AED1E0FA4C7459A648494863E83A548C/04.json"}},"name":"Koopa Cape","authors":["Nintendo"],"slotId":15,"correctSlotId":15,"inCtgp":true,"defaultTrack":true,"200cc":true,"categoryId":4,"trackId":"52F01AE3AED1E0FA4C7459A648494863E83A548C","ghostCount":5125,"uniquePlayers":2984,"popularity":11,"lastChanged":"2024-10-23T17:48:55Z","fastestTime":"01:37.938030440509","fastestTimeSimple":"01:37.939","fastestTimeLastChange":"2024-01-27T15:08:13Z"},{"_links":{"item":{"href":"/leaderboard/0F/52F01AE3AED1E0FA4C7459A648494863E83A548C/05.json"}},"name":"Koopa Cape","authors":["Nintendo"],"slotId":15,"correctSlotId":15,"inCtgp":true,"defaultTrack":true,"200cc":true,"categoryId":5,"trackId":"52F01AE3AED1E0FA4C7459A648494863E83A548C","ghostCount":174,"uniquePlayers":34,"popularity":1,"lastChanged":"2024-10-17T00:09:59Z","fastestTime":"00:49.630244227469","fastestTimeSimple":"00:49.631","fastestTimeLastChange":"2024-04-26T21:14:59Z"},{"_links":{"item":{"href":"/leaderboard/0B/48EBD9D64413C2B98D2B92E5EFC9B15ECD76FEE6/04.json"}},"name":"Maple Treeway","authors":["Nintendo"],"slotId":11,"correctSlotId":11,"inCtgp":true,"defaultTrack":true,"200cc":true,"categoryId":4,"trackId":"48EBD9D64413C2B98D2B92E5EFC9B15ECD76FEE6","ghostCount":3724,"uniquePlayers":2110,"popularity":9,"lastChanged":"2024-10-22T09:46:57Z","fastestTime":"01:39.931580766857","fastestTimeSimple":"01:39.932","fastestTimeLastChange":"2024-01-19T22:36:53Z"},{"_links":{"item":{"href":"/leaderboard/0B/48EBD9D64413C2B98D2B92E5EFC9B15ECD76FEE6/05.json"}},"name":"Maple Treeway","authors":["Nintendo"],"slotId":11,"correctSlotId":11,"inCtgp":true,"defaultTrack":true,"200cc":true,"categoryId":5,"trackId":"48EBD9D64413C2B98D2B92E5EFC9B15ECD76FEE6","ghostCount":327,"uniquePlayers":110,"popularity":0,"lastChanged":"2024-08-31T12:46:01Z","fastestTime":"01:05.956787294850","fastestTimeSimple":"01:05.957","fastestTimeLastChange":"2023-05-14T03:48:53Z"},{"_links":{"item":{"href":"/leaderboard/03/ACC0883AE0CE7879C6EFBA20CFE5B5909BF7841B/04.json"}},"name":"Grumble Volcano","authors":["Nintendo"],"slotId":3,"correctSlotId":3,"inCtgp":true,"defaultTrack":true,"200cc":true,"categoryId":4,"trackId":"ACC0883AE0CE7879C6EFBA20CFE5B5909BF7841B","ghostCount":2749,"uniquePlayers":1334,"popularity":3,"lastChanged":"2024-10-26T19:27:57Z","fastestTime":"01:10.741896301918","fastestTimeSimple":"01:10.742","fastestTimeLastChange":"2023-12-18T14:55:26Z"},{"_links":{"item":{"href":"/leaderboard/03/ACC0883AE0CE7879C6EFBA20CFE5B5909BF7841B/05.json"}},"name":"Grumble Volcano","authors":["Nintendo"],"slotId":3,"correctSlotId":3,"inCtgp":true,"defaultTrack":true,"200cc":true,"categoryId":5,"trackId":"ACC0883AE0CE7879C6EFBA20CFE5B5909BF7841B","ghostCount":7399,"uniquePlayers":2791,"popularity":19,"lastChanged":"2024-10-25T20:18:44Z","fastestTime":"00:18.980505694926","fastestTimeSimple":"00:18.981","fastestTimeLastChange":"2022-08-26T00:11:07Z"},{"_links":{"item":{"href":"/leaderboard/03/ACC0883AE0CE7879C6EFBA20CFE5B5909BF7841B/06.json"}},"name":"Grumble Volcano","authors":["Nintendo"],"slotId":3,"correctSlotId":3,"inCtgp":true,"defaultTrack":true,"200cc":true,"categoryId":6,"trackId":"ACC0883AE0CE7879C6EFBA20CFE5B5909BF7841B","ghostCount":2540,"uniquePlayers":1423,"popularity":7,"lastChanged":"2024-10-25T00:42:57Z","fastestTime":"01:16.891043323577","fastestTimeSimple":"01:16.892","fastestTimeLastChange":"2023-12-30T21:13:12Z"},{"_links":{"item":{"href":"/leaderboard/0E/38486C4F706395772BD988C1AC5FA30D27CAE098/04.json"}},"name":"Dry Dry Ruins","authors":["Nintendo"],"slotId":14,"correctSlotId":14,"inCtgp":true,"defaultTrack":true,"200cc":true,"trackId":"38486C4F706395772BD988C1AC5FA30D27CAE098","ghostCount":6291,"uniquePlayers":3079,"popularity":14,"lastChanged":"2024-10-20T21:03:03Z","fastestTime":"01:15.241959911287","fastestTimeSimple":"01:15.242","fastestTimeLastChange":"2023-07-23T20:54:22Z"},{"_links":{"item":{"href":"/leaderboard/0A/B13C515475D7DA207DFD5BADD886986147B906FF/04.json"}},"name":"Moonview Highway","authors":["Nintendo"],"slotId":10,"correctSlotId":10,"inCtgp":true,"defaultTrack":true,"200cc":true,"categoryId":4,"trackId":"B13C515475D7DA207DFD5BADD886986147B906FF","ghostCount":3280,"uniquePlayers":1816,"popularity":8,"lastChanged":"2024-10-26T19:28:00Z","fastestTime":"01:09.232316897631","fastestTimeSimple":"01:09.233","fastestTimeLastChange":"2023-04-05T16:18:07Z"},{"_links":{"item":{"href":"/leaderboard/0C/B9821B14A89381F9C015669353CB24D7DB1BB25D/04.json"}},"name":"Bowser's Castle","authors":["Nintendo"],"slotId":12,"correctSlotId":12,"inCtgp":true,"defaultTrack":true,"200cc":true,"categoryId":4,"trackId":"B9821B14A89381F9C015669353CB24D7DB1BB25D","ghostCount":761,"uniquePlayers":440,"popularity":4,"lastChanged":"2024-10-21T20:21:45Z","fastestTime":"01:32.090722002655","fastestTimeSimple":"01:32.091","fastestTimeLastChange":"2022-04-28T23:14:05Z"},{"_links":{"item":{"href":"/leaderboard/0C/B9821B14A89381F9C015669353CB24D7DB1BB25D/05.json"}},"name":"Bowser's Castle","authors":["Nintendo"],"slotId":12,"correctSlotId":12,"inCtgp":true,"defaultTrack":true,"200cc":true,"categoryId":5,"trackId":"B9821B14A89381F9C015669353CB24D7DB1BB25D","ghostCount":334,"uniquePlayers":106,"popularity":3,"lastChanged":"2024-10-21T09:56:29Z","fastestTime":"01:20.982445869625","fastestTimeSimple":"01:20.983","fastestTimeLastChange":"2023-08-29T01:52:55Z"},{"_links":{"item":{"href":"/leaderboard/0C/B9821B14A89381F9C015669353CB24D7DB1BB25D/06.json"}},"name":"Bowser's Castle","authors":["Nintendo"],"slotId":12,"correctSlotId":12,"inCtgp":true,"defaultTrack":true,"200cc":true,"categoryId":6,"trackId":"B9821B14A89381F9C015669353CB24D7DB1BB25D","ghostCount":2905,"uniquePlayers":1673,"popularity":10,"lastChanged":"2024-10-22T19:10:53Z","fastestTime":"01:40.127125552297","fastestTimeSimple":"01:40.128","fastestTimeLastChange":"2024-04-23T20:59:59Z"},{"_links":{"item":{"href":"/leaderboard/0D/FFE518915E5FAAA889057C8A3D3E439868574508/04.json"}},"name":"Rainbow Road","authors":["Nintendo"],"slotId":13,"correctSlotId":13,"inCtgp":true,"defaultTrack":true,"200cc":true,"categoryId":4,"trackId":"FFE518915E5FAAA889057C8A3D3E439868574508","ghostCount":5961,"uniquePlayers":3240,"popularity":20,"lastChanged":"2024-10-22T23:25:57Z","fastestTime":"01:44.655160310686","fastestTimeSimple":"01:44.656","fastestTimeLastChange":"2023-12-03T23:40:23Z"},{"_links":{"item":{"href":"/leaderboard/0D/FFE518915E5FAAA889057C8A3D3E439868574508/05.json"}},"name":"Rainbow Road","authors":["Nintendo"],"slotId":13,"correctSlotId":13,"inCtgp":true,"defaultTrack":true,"200cc":true,"categoryId":5,"trackId":"FFE518915E5FAAA889057C8A3D3E439868574508","ghostCount":161,"uniquePlayers":47,"popularity":2,"lastChanged":"2024-10-24T11:06:35Z","fastestTime":"01:26.213088109732","fastestTimeSimple":"01:26.214","fastestTimeLastChange":"2023-07-18T06:38:10Z"},{"_links":{"item":{"href":"/leaderboard/10/8014488A60F4428EEF52D01F8C5861CA9565E1CA/04.json"}},"name":"GCN Peach Beach","authors":["Nintendo"],"slotId":16,"correctSlotId":16,"inCtgp":true,"defaultTrack":true,"200cc":true,"categoryId":4,"trackId":"8014488A60F4428EEF52D01F8C5861CA9565E1CA","ghostCount":11252,"uniquePlayers":3868,"popularity":23,"lastChanged":"2024-10-25T18:37:11Z","fastestTime":"00:48.435427886605","fastestTimeSimple":"00:48.436","fastestTimeLastChange":"2022-02-13T01:36:07Z"},{"_links":{"item":{"href":"/leaderboard/10/8014488A60F4428EEF52D01F8C5861CA9565E1CA/05.json"}},"name":"GCN Peach Beach","authors":["Nintendo"],"slotId":16,"correctSlotId":16,"inCtgp":true,"defaultTrack":true,"200cc":true,"categoryId":5,"trackId":"8014488A60F4428EEF52D01F8C5861CA9565E1CA","ghostCount":110,"uniquePlayers":34,"popularity":0,"lastChanged":"2024-09-09T17:37:47Z","fastestTime":"00:41.580627189219","fastestTimeSimple":"00:41.581","fastestTimeLastChange":"2024-02-08T04:14:23Z"},{"_links":{"item":{"href":"/leaderboard/14/8C854B087417A92425110CC71E23C944D6997806/04.json"}},"name":"DS Yoshi Falls","authors":["Nintendo"],"slotId":20,"correctSlotId":20,"inCtgp":true,"defaultTrack":true,"200cc":true,"trackId":"8C854B087417A92425110CC71E23C944D6997806","ghostCount":18362,"uniquePlayers":5918,"popularity":40,"lastChanged":"2024-10-26T20:52:47Z","fastestTime":"00:38.931280643165","fastestTimeSimple":"00:38.932","fastestTimeLastChange":"2023-02-09T14:40:57Z"},{"_links":{"item":{"href":"/leaderboard/19/071D697C4DDB66D3B210F36C7BF878502E79845B/04.json"}},"name":"SNES Ghost Valley 2","authors":["Nintendo"],"slotId":25,"correctSlotId":25,"inCtgp":true,"defaultTrack":true,"200cc":true,"categoryId":4,"trackId":"071D697C4DDB66D3B210F36C7BF878502E79845B","ghostCount":11431,"uniquePlayers":4367,"popularity":26,"lastChanged":"2024-10-26T09:12:01Z","fastestTime":"00:35.721654239804","fastestTimeSimple":"00:35.722","fastestTimeLastChange":"2023-12-07T22:16:00Z"},{"_links":{"item":{"href":"/leaderboard/19/071D697C4DDB66D3B210F36C7BF878502E79845B/05.json"}},"name":"SNES Ghost Valley 2","authors":["Nintendo"],"slotId":25,"correctSlotId":25,"inCtgp":true,"defaultTrack":true,"200cc":true,"categoryId":5,"trackId":"071D697C4DDB66D3B210F36C7BF878502E79845B","ghostCount":173,"uniquePlayers":90,"popularity":0,"lastChanged":"2024-09-19T04:20:38Z","fastestTime":"00:36.748783628166","fastestTimeSimple":"00:36.749","fastestTimeLastChange":"2019-01-13T08:46:13Z"},{"_links":{"item":{"href":"/leaderboard/1A/49514E8F74FEA50E77273C0297086D67E58123E8/04.json"}},"name":"N64 Mario Raceway","authors":["Nintendo"],"slotId":26,"correctSlotId":26,"inCtgp":true,"defaultTrack":true,"200cc":true,"trackId":"49514E8F74FEA50E77273C0297086D67E58123E8","ghostCount":14241,"uniquePlayers":5698,"popularity":35,"lastChanged":"2024-10-26T20:54:57Z","fastestTime":"01:08.802917306967","fastestTimeSimple":"01:08.803","fastestTimeLastChange":"2024-01-10T17:40:05Z"},{"_links":{"item":{"href":"/leaderboard/1B/BA9BCFB3731A6CB17DBA219A8D37EA4D52332256/04.json"}},"name":"N64 Sherbet Land","authors":["Nintendo"],"slotId":27,"correctSlotId":27,"inCtgp":true,"defaultTrack":true,"200cc":true,"categoryId":4,"trackId":"BA9BCFB3731A6CB17DBA219A8D37EA4D52332256","ghostCount":2327,"uniquePlayers":1327,"popularity":8,"lastChanged":"2024-10-23T01:52:20Z","fastestTime":"01:25.164376416147","fastestTimeSimple":"01:25.165","fastestTimeLastChange":"2023-04-21T17:35:04Z"},{"_links":{"item":{"href":"/leaderboard/1B/BA9BCFB3731A6CB17DBA219A8D37EA4D52332256/05.json"}},"name":"N64 Sherbet Land","authors":["Nintendo"],"slotId":27,"correctSlotId":27,"inCtgp":true,"defaultTrack":true,"200cc":true,"categoryId":5,"trackId":"BA9BCFB3731A6CB17DBA219A8D37EA4D52332256","ghostCount":114,"uniquePlayers":23,"popularity":0,"lastChanged":"2024-09-12T08:36:51Z","fastestTime":"00:32.251158163130","fastestTimeSimple":"00:32.252","fastestTimeLastChange":"2023-07-11T00:14:48Z"},{"_links":{"item":{"href":"/leaderboard/1F/E8ED31605CC7D6660691998F024EED6BA8B4A33F/04.json"}},"name":"GBA Shy Guy Beach","authors":["Nintendo"],"slotId":31,"correctSlotId":31,"inCtgp":true,"defaultTrack":true,"200cc":true,"categoryId":4,"trackId":"E8ED31605CC7D6660691998F024EED6BA8B4A33F","ghostCount":6732,"uniquePlayers":2558,"popularity":15,"lastChanged":"2024-10-25T00:51:46Z","fastestTime":"00:54.067415416181","fastestTimeSimple":"00:54.068","fastestTimeLastChange":"2024-02-19T23:09:13Z"},{"_links":{"item":{"href":"/leaderboard/1F/E8ED31605CC7D6660691998F024EED6BA8B4A33F/05.json"}},"name":"GBA Shy Guy Beach","authors":["Nintendo"],"slotId":31,"correctSlotId":31,"inCtgp":true,"defaultTrack":true,"200cc":true,"categoryId":5,"trackId":"E8ED31605CC7D6660691998F024EED6BA8B4A33F","ghostCount":265,"uniquePlayers":48,"popularity":0,"lastChanged":"2024-10-03T23:20:27Z","fastestTime":"00:52.283173573971","fastestTimeSimple":"00:52.284","fastestTimeLastChange":"2022-07-21T01:41:06Z"},{"_links":{"item":{"href":"/leaderboard/17/BC038E163D21D9A1181B60CF90B4D03EFAD9E0C5/04.json"}},"name":"DS Delfino Square","authors":["Nintendo"],"slotId":23,"correctSlotId":23,"inCtgp":true,"defaultTrack":true,"200cc":true,"trackId":"BC038E163D21D9A1181B60CF90B4D03EFAD9E0C5","ghostCount":6535,"uniquePlayers":3375,"popularity":15,"lastChanged":"2024-10-26T14:57:13Z","fastestTime":"01:22.433160919845","fastestTimeSimple":"01:22.434","fastestTimeLastChange":"2023-02-02T20:54:19Z"},{"_links":{"item":{"href":"/leaderboard/12/418099824AF6BF1CD7F8BB44F61E3A9CC3007DAE/04.json"}},"name":"GCN Waluigi Stadium","authors":["Nintendo"],"slotId":18,"correctSlotId":18,"inCtgp":true,"defaultTrack":true,"200cc":true,"categoryId":4,"trackId":"418099824AF6BF1CD7F8BB44F61E3A9CC3007DAE","ghostCount":6386,"uniquePlayers":3074,"popularity":22,"lastChanged":"2024-10-26T22:19:59Z","fastestTime":"01:19.520393732548","fastestTimeSimple":"01:19.521","fastestTimeLastChange":"2022-09-27T12:10:03Z"},{"_links":{"item":{"href":"/leaderboard/12/418099824AF6BF1CD7F8BB44F61E3A9CC3007DAE/05.json"}},"name":"GCN Waluigi Stadium","authors":["Nintendo"],"slotId":18,"correctSlotId":18,"inCtgp":true,"defaultTrack":true,"200cc":true,"categoryId":5,"trackId":"418099824AF6BF1CD7F8BB44F61E3A9CC3007DAE","ghostCount":146,"uniquePlayers":45,"popularity":1,"lastChanged":"2024-10-10T23:31:24Z","fastestTime":"00:58.153543471873","fastestTimeSimple":"00:58.154","fastestTimeLastChange":"2024-06-14T04:39:59Z"},{"_links":{"item":{"href":"/leaderboard/15/4EC538065FDC8ACF49674300CBDEC5B80CC05A0D/04.json"}},"name":"DS Desert Hills","authors":["Nintendo"],"slotId":21,"correctSlotId":21,"inCtgp":true,"defaultTrack":true,"200cc":true,"categoryId":4,"trackId":"4EC538065FDC8ACF49674300CBDEC5B80CC05A0D","ghostCount":199,"uniquePlayers":111,"popularity":0,"lastChanged":"2024-08-19T21:23:53Z","fastestTime":"01:08.000308371246","fastestTimeSimple":"01:08.001","fastestTimeLastChange":"2019-05-05T18:11:00Z"},{"_links":{"item":{"href":"/leaderboard/15/4EC538065FDC8ACF49674300CBDEC5B80CC05A0D/06.json"}},"name":"DS Desert Hills","authors":["Nintendo"],"slotId":21,"correctSlotId":21,"inCtgp":true,"defaultTrack":true,"200cc":true,"categoryId":6,"trackId":"4EC538065FDC8ACF49674300CBDEC5B80CC05A0D","ghostCount":5168,"uniquePlayers":2398,"popularity":18,"lastChanged":"2024-10-26T14:37:06Z","fastestTime":"01:03.860416349947","fastestTimeSimple":"01:03.861","fastestTimeLastChange":"2023-02-06T21:07:54Z"},{"_links":{"item":{"href":"/leaderboard/1E/A4BEA41BE83D816F793F3FAD97D268F71AD99BF9/04.json"}},"name":"GBA Bowser Castle 3","authors":["Nintendo"],"slotId":30,"correctSlotId":30,"inCtgp":true,"defaultTrack":true,"200cc":true,"categoryId":4,"trackId":"A4BEA41BE83D816F793F3FAD97D268F71AD99BF9","ghostCount":1956,"uniquePlayers":1153,"popularity":8,"lastChanged":"2024-10-25T06:24:20Z","fastestTime":"01:24.006240091503","fastestTimeSimple":"01:24.007","fastestTimeLastChange":"2024-01-29T17:21:04Z"},{"_links":{"item":{"href":"/leaderboard/1E/A4BEA41BE83D816F793F3FAD97D268F71AD99BF9/05.json"}},"name":"GBA Bowser Castle 3","authors":["Nintendo"],"slotId":30,"correctSlotId":30,"inCtgp":true,"defaultTrack":true,"200cc":true,"categoryId":5,"trackId":"A4BEA41BE83D816F793F3FAD97D268F71AD99BF9","ghostCount":6,"uniquePlayers":3,"popularity":0,"lastChanged":"2024-05-04T22:58:15Z","fastestTime":"01:56.977398787737","fastestTimeSimple":"01:56.978","fastestTimeLastChange":"2024-05-01T18:55:07Z"},{"_links":{"item":{"href":"/leaderboard/1E/A4BEA41BE83D816F793F3FAD97D268F71AD99BF9/06.json"}},"name":"GBA Bowser Castle 3","authors":["Nintendo"],"slotId":30,"correctSlotId":30,"inCtgp":true,"defaultTrack":true,"200cc":true,"categoryId":6,"trackId":"A4BEA41BE83D816F793F3FAD97D268F71AD99BF9","ghostCount":3687,"uniquePlayers":1910,"popularity":10,"lastChanged":"2024-10-23T21:36:24Z","fastestTime":"01:32.869949871838","fastestTimeSimple":"01:32.870","fastestTimeLastChange":"2024-02-19T23:09:13Z"},{"_links":{"item":{"href":"/leaderboard/1D/692D566B05434D8C66A55BDFF486698E0FC96095/04.json"}},"name":"N64 DK's Jungle Parkway","authors":["Nintendo"],"slotId":29,"correctSlotId":29,"inCtgp":true,"defaultTrack":true,"200cc":true,"categoryId":4,"trackId":"692D566B05434D8C66A55BDFF486698E0FC96095","ghostCount":502,"uniquePlayers":224,"popularity":2,"lastChanged":"2024-10-15T00:44:38Z","fastestTime":"01:36.542349202573","fastestTimeSimple":"01:36.543","fastestTimeLastChange":"2023-12-31T19:47:45Z"},{"_links":{"item":{"href":"/leaderboard/1D/692D566B05434D8C66A55BDFF486698E0FC96095/05.json"}},"name":"N64 DK's Jungle Parkway","authors":["Nintendo"],"slotId":29,"correctSlotId":29,"inCtgp":true,"defaultTrack":true,"200cc":true,"categoryId":5,"trackId":"692D566B05434D8C66A55BDFF486698E0FC96095","ghostCount":350,"uniquePlayers":86,"popularity":2,"lastChanged":"2024-10-16T03:35:33Z","fastestTime":"00:51.276003237605","fastestTimeSimple":"00:51.277","fastestTimeLastChange":"2023-09-06T16:24:59Z"},{"_links":{"item":{"href":"/leaderboard/1D/692D566B05434D8C66A55BDFF486698E0FC96095/06.json"}},"name":"N64 DK's Jungle Parkway","authors":["Nintendo"],"slotId":29,"correctSlotId":29,"inCtgp":true,"defaultTrack":true,"200cc":true,"categoryId":6,"trackId":"692D566B05434D8C66A55BDFF486698E0FC96095","ghostCount":2436,"uniquePlayers":1197,"popularity":11,"lastChanged":"2024-10-26T19:27:56Z","fastestTime":"01:38.825839318305","fastestTimeSimple":"01:38.826","fastestTimeLastChange":"2024-06-22T15:55:08Z"},{"_links":{"item":{"href":"/leaderboard/11/1941A29AD2E7B7BBA8A29E6440C95EF5CF76B01D/05.json"}},"name":"GCN Mario Circuit","authors":["Nintendo"],"slotId":17,"correctSlotId":17,"inCtgp":true,"defaultTrack":true,"200cc":true,"categoryId":5,"trackId":"1941A29AD2E7B7BBA8A29E6440C95EF5CF76B01D","ghostCount":20,"uniquePlayers":12,"popularity":1,"lastChanged":"2024-05-30T22:08:13Z","fastestTime":"01:11.191257013977","fastestTimeSimple":"01:11.192","fastestTimeLastChange":"2021-09-08T18:21:35Z"},{"_links":{"item":{"href":"/leaderboard/11/1941A29AD2E7B7BBA8A29E6440C95EF5CF76B01D/06.json"}},"name":"GCN Mario Circuit","authors":["Nintendo"],"slotId":17,"correctSlotId":17,"inCtgp":true,"defaultTrack":true,"200cc":true,"categoryId":6,"trackId":"1941A29AD2E7B7BBA8A29E6440C95EF5CF76B01D","ghostCount":3207,"uniquePlayers":1728,"popularity":10,"lastChanged":"2024-10-23T01:52:27Z","fastestTime":"01:04.819518295228","fastestTimeSimple":"01:04.820","fastestTimeLastChange":"2024-05-17T21:50:33Z"},{"_links":{"item":{"href":"/leaderboard/18/077111B996E5C4F47D20EC29C2938504B53A8E76/04.json"}},"name":"SNES Mario Circuit 3","authors":["Nintendo"],"slotId":24,"correctSlotId":24,"inCtgp":true,"defaultTrack":true,"200cc":true,"categoryId":4,"trackId":"077111B996E5C4F47D20EC29C2938504B53A8E76","ghostCount":8709,"uniquePlayers":3284,"popularity":23,"lastChanged":"2024-10-26T14:57:14Z","fastestTime":"00:54.377225181878","fastestTimeSimple":"00:54.378","fastestTimeLastChange":"2023-05-16T22:00:58Z"},{"_links":{"item":{"href":"/leaderboard/16/F9A62BEF04CC8F499633E4023ACC7675A92771F0/04.json"}},"name":"DS Peach Gardens","authors":["Nintendo"],"slotId":22,"correctSlotId":22,"inCtgp":true,"defaultTrack":true,"200cc":true,"categoryId":4,"trackId":"F9A62BEF04CC8F499633E4023ACC7675A92771F0","ghostCount":2494,"uniquePlayers":1408,"popularity":7,"lastChanged":"2024-10-23T04:20:04Z","fastestTime":"01:21.626528257221","fastestTimeSimple":"01:21.627","fastestTimeLastChange":"2023-03-25T22:48:42Z"},{"_links":{"item":{"href":"/leaderboard/16/F9A62BEF04CC8F499633E4023ACC7675A92771F0/05.json"}},"name":"DS Peach Gardens","authors":["Nintendo"],"slotId":22,"correctSlotId":22,"inCtgp":true,"defaultTrack":true,"200cc":true,"categoryId":5,"trackId":"F9A62BEF04CC8F499633E4023ACC7675A92771F0","ghostCount":4,"uniquePlayers":1,"popularity":1,"lastChanged":"2024-09-21T07:36:59Z","fastestTime":"01:35.147468733549","fastestTimeSimple":"01:35.148","fastestTimeLastChange":"2024-09-21T07:36:59Z"},{"_links":{"item":{"href":"/leaderboard/13/B036864CF0016BE0581449EF29FB52B2E58D78A4/04.json"}},"name":"GCN DK Mountain","authors":["Nintendo"],"slotId":19,"correctSlotId":19,"inCtgp":true,"defaultTrack":true,"200cc":true,"categoryId":4,"trackId":"B036864CF0016BE0581449EF29FB52B2E58D78A4","ghostCount":206,"uniquePlayers":114,"popularity":1,"lastChanged":"2024-09-01T00:04:09Z","fastestTime":"01:36.583504055888","fastestTimeSimple":"01:36.584","fastestTimeLastChange":"2024-01-24T02:35:15Z"},{"_links":{"item":{"href":"/leaderboard/13/B036864CF0016BE0581449EF29FB52B2E58D78A4/06.json"}},"name":"GCN DK Mountain","authors":["Nintendo"],"slotId":19,"correctSlotId":19,"inCtgp":true,"defaultTrack":true,"200cc":true,"categoryId":6,"trackId":"B036864CF0016BE0581449EF29FB52B2E58D78A4","ghostCount":3978,"uniquePlayers":2127,"popularity":20,"lastChanged":"2024-10-26T19:27:58Z","fastestTime":"01:38.095287221968","fastestTimeSimple":"01:38.096","fastestTimeLastChange":"2022-02-10T03:58:34Z"},{"_links":{"item":{"href":"/leaderboard/1C/15B303B288F4707E5D0AF28367C8CE51CDEAB490/04.json"}},"name":"N64 Bowser's Castle","authors":["Nintendo"],"slotId":28,"correctSlotId":28,"inCtgp":true,"defaultTrack":true,"200cc":true,"categoryId":4,"trackId":"15B303B288F4707E5D0AF28367C8CE51CDEAB490","ghostCount":63,"uniquePlayers":16,"popularity":0,"lastChanged":"2024-08-23T01:43:54Z","fastestTime":"01:51.313251447082","fastestTimeSimple":"01:51.314","fastestTimeLastChange":"2022-12-29T14:53:16Z"},{"_links":{"item":{"href":"/leaderboard/1C/15B303B288F4707E5D0AF28367C8CE51CDEAB490/05.json"}},"name":"N64 Bowser's Castle","authors":["Nintendo"],"slotId":28,"correctSlotId":28,"inCtgp":true,"defaultTrack":true,"200cc":true,"categoryId":5,"trackId":"15B303B288F4707E5D0AF28367C8CE51CDEAB490","ghostCount":76,"uniquePlayers":24,"popularity":1,"lastChanged":"2024-10-08T01:05:10Z","fastestTime":"01:33.460511438727","fastestTimeSimple":"01:33.461","fastestTimeLastChange":"2023-06-24T19:05:14Z"},{"_links":{"item":{"href":"/leaderboard/1C/15B303B288F4707E5D0AF28367C8CE51CDEAB490/06.json"}},"name":"N64 Bowser's Castle","authors":["Nintendo"],"slotId":28,"correctSlotId":28,"inCtgp":true,"defaultTrack":true,"200cc":true,"categoryId":6,"trackId":"15B303B288F4707E5D0AF28367C8CE51CDEAB490","ghostCount":5625,"uniquePlayers":2986,"popularity":18,"lastChanged":"2024-10-26T15:09:56Z","fastestTime":"01:45.154469009936","fastestTimeSimple":"01:45.155","fastestTimeLastChange":"2023-03-18T12:47:09Z"}],"lastUpdated":"2024-10-26T22:26:59.040Z"}