[{"status":"fulfilled","value":{"_links":{"self":{"href":"/leaderboard/08/1AE1A7D894960B38E09E7494373378D87305A163/04.json"},"index":{"href":"/leaderboards.json"},"leaderboardFastLap":{"href":"/leaderboard/08/1AE1A7D894960B38E09E7494373378D87305A163/04-fast-lap.json"}},"name":"Luigi Circuit","authors":["Nintendo"],"slotId":8,"correctSlotId":8,"inCtgp":true,"defaultTrack":true,"200cc":true,"categoryId":4,"trackId":"1AE1A7D894960B38E09E7494373378D87305A163","ghostCount":64806,"ghosts":[{"_links":{"item":{"href":"/rkgd/BE/7C/EC2822E88E29C5ABCA752AA6EE753AD4A31F.json"},"player":{"href":"/players/40/54922A89F5551F.json"}},"href":"/rkgd/BE/7C/EC2822E88E29C5ABCA752AA6EE753AD4A31F.rkg","playerId":"4054922A89F5551F","finishTime":"00:46.258143377125","finishTimeSimple":"00:46.259","hash":"BE7CEC2822E88E29C5ABCA752AA6EE753AD4A31F","vehicleId":23,"driverId":22,"controller":3,"usbGcnAdapterAttached":false,"player":"Besart F.","playersFastest":true,"leaderboardPlayerId":0,"dateSet":"2023-05-17T21:27:54Z","wasWr":true}],"uniquePlayers":22471,"popularity":57,"lastChanged":"2025-09-24T09:51:21Z","fastestTime":"00:46.258143377125","fastestTimeSimple":"00:46.259","fastestTimeLastChange":"2023-05-17T21:27:54Z"}},{"status":"fulfilled","value":{"_links":{"self":{"href":"/leaderboard/01/90720A7D57A7C76E2347782F6BDE5D22342FB7DD/04.json"},"index":{"href":"/leaderboards.json"},"leaderboardFastLap":{"href":"/leaderboard/01/90720A7D57A7C76E2347782F6BDE5D22342FB7DD/04-fast-lap.json"}},"name":"Moo Moo Meadows","authors":["Nintendo"],"slotId":1,"correctSlotId":1,"inCtgp":true,"defaultTrack":true,"200cc":true,"categoryId":4,"trackId":"90720A7D57A7C76E2347782F6BDE5D22342FB7DD","ghostCount":16669,"ghosts":[{"_links":{"item":{"href":"/rkgd/70/40/2B045C17F492387B294D5468826537FE8610.json"},"player":{"href":"/players/D3/1D0B090D52771B.json"}},"href":"/rkgd/70/40/2B045C17F492387B294D5468826537FE8610.rkg","playerId":"D31D0B090D52771B","finishTime":"00:50.979475157380","finishTimeSimple":"00:50.980","hash":"70402B045C17F492387B294D5468826537FE8610","vehicleId":23,"driverId":22,"controller":2,"usbGcnAdapterAttached":false,"player":"woah","playersFastest":true,"leaderboardPlayerId":0,"dateSet":"2024-11-04T22:21:48Z","wasWr":true}],"uniquePlayers":7413,"popularity":15,"lastChanged":"2025-09-23T05:27:49Z","fastestTime":"00:50.979475157380","fastestTimeSimple":"00:50.980","fastestTimeLastChange":"2024-11-04T22:21:48Z"}},{"status":"fulfilled","value":{"_links":{"self":{"href":"/leaderboard/02/0E380357AFFCFD8722329994885699D9927F8276/04.json"},"index":{"href":"/leaderboards.json"},"leaderboardFastLap":{"href":"/leaderboard/02/0E380357AFFCFD8722329994885699D9927F8276/04-fast-lap.json"}},"name":"Mushroom Gorge","authors":["Nintendo"],"slotId":2,"correctSlotId":2,"inCtgp":true,"defaultTrack":true,"200cc":true,"categoryId":4,"trackId":"0E380357AFFCFD8722329994885699D9927F8276","ghostCount":997,"ghosts":[{"_links":{"item":{"href":"/rkgd/0D/A7/F87A5D5501F3C11070DB7185B5CCB1DCF6C8.json"},"player":{"href":"/players/1C/6A832CF6B30CFF.json"}},"href":"/rkgd/0D/A7/F87A5D5501F3C11070DB7185B5CCB1DCF6C8.rkg","playerId":"1C6A832CF6B30CFF","finishTime":"01:14.918521849453","finishTimeSimple":"01:14.919","hash":"0DA7F87A5D5501F3C11070DB7185B5CCB1DCF6C8","vehicleId":23,"driverId":22,"controller":0,"usbGcnAdapterAttached":false,"country":82,"region":3,"player":"sy Elec","continent":3,"playersFastest":true,"leaderboardPlayerId":0,"dateSet":"2024-05-03T21:44:31Z","wasWr":true}],"uniquePlayers":651,"popularity":2,"lastChanged":"2025-09-06T21:25:58Z","fastestTime":"01:14.918521849453","fastestTimeSimple":"01:14.919","fastestTimeLastChange":"2024-05-03T21:44:31Z"}},{"status":"fulfilled","value":{"_links":{"self":{"href":"/leaderboard/02/0E380357AFFCFD8722329994885699D9927F8276/05.json"},"index":{"href":"/leaderboards.json"},"leaderboardFastLap":{"href":"/leaderboard/02/0E380357AFFCFD8722329994885699D9927F8276/05-fast-lap.json"}},"name":"Mushroom Gorge","authors":["Nintendo"],"slotId":2,"correctSlotId":2,"inCtgp":true,"defaultTrack":true,"200cc":true,"categoryId":5,"trackId":"0E380357AFFCFD8722329994885699D9927F8276","ghostCount":2232,"ghosts":[{"_links":{"item":{"href":"/rkgd/0B/38/A96FB03224242C8B6FA593BF266D5D30C838.json"},"player":{"href":"/players/9B/376538E2E5D4AF.json"}},"href":"/rkgd/0B/38/A96FB03224242C8B6FA593BF266D5D30C838.rkg","playerId":"9B376538E2E5D4AF","finishTime":"00:24.261116594374","finishTimeSimple":"00:24.262","hash":"0B38A96FB03224242C8B6FA593BF266D5D30C838","vehicleId":27,"driverId":14,"controller":0,"usbGcnAdapterAttached":false,"country":49,"region":7,"player":"NL☆Rίçhβδγ","continent":2,"playersFastest":true,"leaderboardPlayerId":0,"dateSet":"2019-07-18T18:46:14Z","wasWr":true}],"uniquePlayers":983,"popularity":2,"lastChanged":"2025-09-21T10:10:43Z","fastestTime":"00:24.261116594374","fastestTimeSimple":"00:24.262","fastestTimeLastChange":"2019-07-18T18:46:14Z"}},{"status":"fulfilled","value":{"_links":{"self":{"href":"/leaderboard/02/0E380357AFFCFD8722329994885699D9927F8276/06.json"},"index":{"href":"/leaderboards.json"},"leaderboardFastLap":{"href":"/leaderboard/02/0E380357AFFCFD8722329994885699D9927F8276/06-fast-lap.json"}},"name":"Mushroom Gorge","authors":["Nintendo"],"slotId":2,"correctSlotId":2,"inCtgp":true,"defaultTrack":true,"200cc":true,"categoryId":6,"trackId":"0E380357AFFCFD8722329994885699D9927F8276","ghostCount":28952,"ghosts":[{"_links":{"item":{"href":"/rkgd/4F/13/ECBEB7DCCBCE078FDD6DBD9933F6DF030074.json"},"player":{"href":"/players/D3/1D0B090D52771B.json"}},"href":"/rkgd/4F/13/ECBEB7DCCBCE078FDD6DBD9933F6DF030074.rkg","playerId":"D31D0B090D52771B","finishTime":"01:12.847800728664","finishTimeSimple":"01:12.848","hash":"4F13ECBEB7DCCBCE078FDD6DBD9933F6DF030074","vehicleId":22,"driverId":15,"controller":2,"usbGcnAdapterAttached":false,"player":"woah","playersFastest":true,"leaderboardPlayerId":0,"dateSet":"2024-02-16T01:22:17Z","wasWr":true}],"uniquePlayers":10161,"popularity":22,"lastChanged":"2025-09-22T19:54:26Z","fastestTime":"01:12.847800728664","fastestTimeSimple":"01:12.848","fastestTimeLastChange":"2024-02-16T01:22:17Z"}},{"status":"fulfilled","value":{"_links":{"self":{"href":"/leaderboard/04/1896AEA49617A571C66FF778D8F2ABBE9E5D7479/04.json"},"index":{"href":"/leaderboards.json"},"leaderboardFastLap":{"href":"/leaderboard/04/1896AEA49617A571C66FF778D8F2ABBE9E5D7479/04-fast-lap.json"}},"name":"Toad's Factory","authors":["Nintendo"],"slotId":4,"correctSlotId":4,"inCtgp":true,"defaultTrack":true,"200cc":true,"categoryId":4,"trackId":"1896AEA49617A571C66FF778D8F2ABBE9E5D7479","ghostCount":342,"ghosts":[{"_links":{"item":{"href":"/rkgd/58/13/ABD4BD0E83F4B256B7EF3CD3B3EA50F4006E.json"},"player":{"href":"/players/06/04323F602D1553.json"}},"href":"/rkgd/58/13/ABD4BD0E83F4B256B7EF3CD3B3EA50F4006E.rkg","playerId":"0604323F602D1553","finishTime":"01:15.027827442288","finishTimeSimple":"01:15.028","hash":"5813ABD4BD0E83F4B256B7EF3CD3B3EA50F4006E","vehicleId":22,"driverId":15,"controller":1,"usbGcnAdapterAttached":false,"country":77,"region":17,"player":"Arthur","continent":3,"playersFastest":true,"leaderboardPlayerId":0,"dateSet":"2024-03-01T15:22:54Z","wasWr":true}],"uniquePlayers":199,"popularity":0,"lastChanged":"2024-03-07T17:03:21Z","fastestTime":"01:15.027827442288","fastestTimeSimple":"01:15.028","fastestTimeLastChange":"2024-03-01T15:22:54Z"}},{"status":"fulfilled","value":{"_links":{"self":{"href":"/leaderboard/04/1896AEA49617A571C66FF778D8F2ABBE9E5D7479/06.json"},"index":{"href":"/leaderboards.json"},"leaderboardFastLap":{"href":"/leaderboard/04/1896AEA49617A571C66FF778D8F2ABBE9E5D7479/06-fast-lap.json"}},"name":"Toad's Factory","authors":["Nintendo"],"slotId":4,"correctSlotId":4,"inCtgp":true,"defaultTrack":true,"200cc":true,"categoryId":6,"trackId":"1896AEA49617A571C66FF778D8F2ABBE9E5D7479","ghostCount":18051,"ghosts":[{"_links":{"item":{"href":"/rkgd/A0/07/015A55DF69CBF55F28DDE728930748D9C0E6.json"},"player":{"href":"/players/D3/1D0B090D52771B.json"}},"href":"/rkgd/A0/07/015A55DF69CBF55F28DDE728930748D9C0E6.rkg","playerId":"D31D0B090D52771B","finishTime":"01:15.870158384144","finishTimeSimple":"01:15.871","hash":"A007015A55DF69CBF55F28DDE728930748D9C0E6","vehicleId":22,"driverId":15,"controller":2,"usbGcnAdapterAttached":false,"player":"Schmancy","playersFastest":true,"leaderboardPlayerId":0,"dateSet":"2024-05-11T11:42:56Z","wasWr":true}],"uniquePlayers":8324,"popularity":20,"lastChanged":"2025-09-23T21:31:28Z","fastestTime":"01:15.870158384144","fastestTimeSimple":"01:15.871","fastestTimeLastChange":"2024-05-11T11:42:56Z"}},{"status":"fulfilled","value":{"_links":{"self":{"href":"/leaderboard/00/7752BB51EDBC4A95377C0A05B0E0DA1503786625/04.json"},"index":{"href":"/leaderboards.json"},"leaderboardFastLap":{"href":"/leaderboard/00/7752BB51EDBC4A95377C0A05B0E0DA1503786625/04-fast-lap.json"}},"name":"Mario Circuit","authors":["Nintendo"],"slotId":0,"correctSlotId":0,"inCtgp":true,"defaultTrack":true,"200cc":true,"categoryId":4,"trackId":"7752BB51EDBC4A95377C0A05B0E0DA1503786625","ghostCount":17707,"ghosts":[{"_links":{"item":{"href":"/rkgd/2A/16/7FFA230A2AF070801F776879FDE890A56B90.json"},"player":{"href":"/players/D3/1D0B090D52771B.json"}},"href":"/rkgd/2A/16/7FFA230A2AF070801F776879FDE890A56B90.rkg","playerId":"D31D0B090D52771B","finishTime":"00:53.671115733862","finishTimeSimple":"00:53.672","hash":"2A167FFA230A2AF070801F776879FDE890A56B90","vehicleId":23,"driverId":22,"controller":2,"usbGcnAdapterAttached":false,"player":"Schmancy","playersFastest":true,"leaderboardPlayerId":0,"dateSet":"2024-05-10T16:05:45Z","wasWr":true}],"uniquePlayers":6751,"popularity":23,"lastChanged":"2025-09-22T22:37:53Z","fastestTime":"00:53.671115733862","fastestTimeSimple":"00:53.672","fastestTimeLastChange":"2024-05-10T16:05:45Z"}},{"status":"fulfilled","value":{"_links":{"self":{"href":"/leaderboard/00/7752BB51EDBC4A95377C0A05B0E0DA1503786625/05.json"},"index":{"href":"/leaderboards.json"},"leaderboardFastLap":{"href":"/leaderboard/00/7752BB51EDBC4A95377C0A05B0E0DA1503786625/05-fast-lap.json"}},"name":"Mario Circuit","authors":["Nintendo"],"slotId":0,"correctSlotId":0,"inCtgp":true,"defaultTrack":true,"200cc":true,"categoryId":5,"trackId":"7752BB51EDBC4A95377C0A05B0E0DA1503786625","ghostCount":3396,"ghosts":[{"_links":{"item":{"href":"/rkgd/1F/ED/EC818AD493A60051B6CBB0043293BBC6C17E.json"},"player":{"href":"/players/4B/7D706D8F20A001.json"}},"href":"/rkgd/1F/ED/EC818AD493A60051B6CBB0043293BBC6C17E.rkg","playerId":"4B7D706D8F20A001","finishTime":"00:38.528525957793","finishTimeSimple":"00:38.529","hash":"1FEDEC818AD493A60051B6CBB0043293BBC6C17E","vehicleId":21,"driverId":4,"controller":2,"usbGcnAdapterAttached":false,"country":49,"region":37,"player":"patricio","continent":2,"playersFastest":true,"leaderboardPlayerId":0,"dateSet":"2025-06-30T02:02:00Z","wasWr":true}],"uniquePlayers":1090,"popularity":4,"lastChanged":"2025-09-20T10:56:50Z","fastestTime":"00:38.528525957793","fastestTimeSimple":"00:38.529","fastestTimeLastChange":"2025-06-30T02:02:00Z"}},{"status":"fulfilled","value":{"_links":{"self":{"href":"/leaderboard/05/E4BF364CB0C5899907585D731621CA930A4EF85C/04.json"},"index":{"href":"/leaderboards.json"},"leaderboardFastLap":{"href":"/leaderboard/05/E4BF364CB0C5899907585D731621CA930A4EF85C/04-fast-lap.json"}},"name":"Coconut Mall","authors":["Nintendo"],"slotId":5,"correctSlotId":5,"inCtgp":true,"defaultTrack":true,"200cc":true,"categoryId":4,"trackId":"E4BF364CB0C5899907585D731621CA930A4EF85C","ghostCount":8087,"ghosts":[{"_links":{"item":{"href":"/rkgd/70/4D/2E6C58FF873913B9CF21BB6E2C6B2E7347CC.json"},"player":{"href":"/players/37/35C6FE62F34E96.json"}},"href":"/rkgd/70/4D/2E6C58FF873913B9CF21BB6E2C6B2E7347CC.rkg","playerId":"3735C6FE62F34E96","finishTime":"01:03.848535565615","finishTimeSimple":"01:03.849","hash":"704D2E6C58FF873913B9CF21BB6E2C6B2E7347CC","vehicleId":22,"driverId":15,"controller":2,"usbGcnAdapterAttached":false,"country":94,"region":12,"player":"Ω Indy","continent":3,"playersFastest":true,"leaderboardPlayerId":0,"dateSet":"2024-11-04T18:42:28Z","wasWr":true}],"uniquePlayers":2710,"popularity":4,"lastChanged":"2025-09-21T04:17:04Z","fastestTime":"01:03.848535565615","fastestTimeSimple":"01:03.849","fastestTimeLastChange":"2024-11-04T18:42:28Z"}},{"status":"fulfilled","value":{"_links":{"self":{"href":"/leaderboard/05/E4BF364CB0C5899907585D731621CA930A4EF85C/05.json"},"index":{"href":"/leaderboards.json"},"leaderboardFastLap":{"href":"/leaderboard/05/E4BF364CB0C5899907585D731621CA930A4EF85C/05-fast-lap.json"}},"name":"Coconut Mall","authors":["Nintendo"],"slotId":5,"correctSlotId":5,"inCtgp":true,"defaultTrack":true,"200cc":true,"categoryId":5,"trackId":"E4BF364CB0C5899907585D731621CA930A4EF85C","ghostCount":4779,"ghosts":[{"_links":{"item":{"href":"/rkgd/36/DA/898D1FC3BE0A4D2CA3ECE1D0985CE4D32676.json"},"player":{"href":"/players/1E/C3384B8D39B684.json"}},"href":"/rkgd/36/DA/898D1FC3BE0A4D2CA3ECE1D0985CE4D32676.rkg","playerId":"1EC3384B8D39B684","finishTime":"00:27.376287903309","finishTimeSimple":"00:27.377","hash":"36DA898D1FC3BE0A4D2CA3ECE1D0985CE4D32676","vehicleId":22,"driverId":15,"controller":1,"usbGcnAdapterAttached":false,"country":49,"region":21,"player":"Master☆JCP","continent":2,"playersFastest":true,"leaderboardPlayerId":0,"dateSet":"2023-04-20T19:17:46Z","wasWr":true}],"uniquePlayers":1461,"popularity":3,"lastChanged":"2025-09-21T04:17:06Z","fastestTime":"00:27.376287903309","fastestTimeSimple":"00:27.377","fastestTimeLastChange":"2023-04-20T19:17:46Z"}},{"status":"fulfilled","value":{"_links":{"self":{"href":"/leaderboard/05/E4BF364CB0C5899907585D731621CA930A4EF85C/06.json"},"index":{"href":"/leaderboards.json"},"leaderboardFastLap":{"href":"/leaderboard/05/E4BF364CB0C5899907585D731621CA930A4EF85C/06-fast-lap.json"}},"name":"Coconut Mall","authors":["Nintendo"],"slotId":5,"correctSlotId":5,"inCtgp":true,"defaultTrack":true,"200cc":true,"categoryId":6,"trackId":"E4BF364CB0C5899907585D731621CA930A4EF85C","ghostCount":13244,"ghosts":[{"_links":{"item":{"href":"/rkgd/54/A8/EBC50050C8F8454FD43087EA5BE3FFED20C4.json"},"player":{"href":"/players/D4/609DB8549BBAF2.json"}},"href":"/rkgd/54/A8/EBC50050C8F8454FD43087EA5BE3FFED20C4.rkg","playerId":"D4609DB8549BBAF2","finishTime":"01:14.620494287670","finishTimeSimple":"01:14.621","hash":"54A8EBC50050C8F8454FD43087EA5BE3FFED20C4","vehicleId":22,"driverId":15,"controller":2,"usbGcnAdapterAttached":false,"country":94,"region":6,"player":"Dυçκ E","continent":3,"playersFastest":true,"leaderboardPlayerId":0,"dateSet":"2020-01-02T23:03:55Z","wasWr":true}],"uniquePlayers":6706,"popularity":21,"lastChanged":"2025-09-23T18:51:37Z","fastestTime":"01:14.620494287670","fastestTimeSimple":"01:14.621","fastestTimeLastChange":"2020-01-02T23:03:55Z"}},{"status":"fulfilled","value":{"_links":{"self":{"href":"/leaderboard/06/B02ED72E00B400647BDA6845BE387C47D251F9D1/04.json"},"index":{"href":"/leaderboards.json"},"leaderboardFastLap":{"href":"/leaderboard/06/B02ED72E00B400647BDA6845BE387C47D251F9D1/04-fast-lap.json"}},"name":"DK Summit","authors":["Nintendo"],"slotId":6,"correctSlotId":6,"inCtgp":true,"defaultTrack":true,"200cc":true,"trackId":"B02ED72E00B400647BDA6845BE387C47D251F9D1","ghostCount":16545,"ghosts":[{"_links":{"item":{"href":"/rkgd/DE/8A/29152B8D9267DFA9AE35DF7BFD609F56803B.json"},"player":{"href":"/players/42/48F1A12AB9C849.json"}},"href":"/rkgd/DE/8A/29152B8D9267DFA9AE35DF7BFD609F56803B.rkg","playerId":"4248F1A12AB9C849","finishTime":"01:11.435639016897","finishTimeSimple":"01:11.436","hash":"DE8A29152B8D9267DFA9AE35DF7BFD609F56803B","vehicleId":22,"driverId":15,"controller":2,"usbGcnAdapterAttached":false,"player":"XXXX EEEEE","playersFastest":true,"leaderboardPlayerId":0,"dateSet":"2025-06-05T23:20:07Z","wasWr":true}],"uniquePlayers":7665,"popularity":23,"lastChanged":"2025-09-24T09:51:30Z","fastestTime":"01:11.435639016897","fastestTimeSimple":"01:11.436","fastestTimeLastChange":"2025-06-05T23:20:07Z"}},{"status":"fulfilled","value":{"_links":{"self":{"href":"/leaderboard/07/D1A453B43D6920A78565E65A4597E353B177ABD0/04.json"},"index":{"href":"/leaderboards.json"},"leaderboardFastLap":{"href":"/leaderboard/07/D1A453B43D6920A78565E65A4597E353B177ABD0/04-fast-lap.json"}},"name":"Wario's Gold Mine","authors":["Nintendo"],"slotId":7,"correctSlotId":7,"inCtgp":true,"defaultTrack":true,"200cc":true,"categoryId":4,"trackId":"D1A453B43D6920A78565E65A4597E353B177ABD0","ghostCount":2952,"ghosts":[{"_links":{"item":{"href":"/rkgd/B3/C3/924C99F52D287C79BE8D2F3034C1284549F6.json"},"player":{"href":"/players/D3/1D0B090D52771B.json"}},"href":"/rkgd/B3/C3/924C99F52D287C79BE8D2F3034C1284549F6.rkg","playerId":"D31D0B090D52771B","finishTime":"01:14.552264887810","finishTimeSimple":"01:14.553","hash":"B3C3924C99F52D287C79BE8D2F3034C1284549F6","vehicleId":22,"driverId":15,"controller":1,"usbGcnAdapterAttached":false,"country":110,"region":2,"player":"Schmancy","continent":3,"playersFastest":true,"leaderboardPlayerId":0,"dateSet":"2023-01-22T23:07:16Z","wasWr":true}],"uniquePlayers":1775,"popularity":2,"lastChanged":"2025-09-12T23:45:09Z","fastestTime":"01:14.552264887810","fastestTimeSimple":"01:14.553","fastestTimeLastChange":"2023-01-22T23:07:16Z"}},{"status":"fulfilled","value":{"_links":{"self":{"href":"/leaderboard/07/D1A453B43D6920A78565E65A4597E353B177ABD0/05.json"},"index":{"href":"/leaderboards.json"},"leaderboardFastLap":{"href":"/leaderboard/07/D1A453B43D6920A78565E65A4597E353B177ABD0/05-fast-lap.json"}},"name":"Wario's Gold Mine","authors":["Nintendo"],"slotId":7,"correctSlotId":7,"inCtgp":true,"defaultTrack":true,"200cc":true,"categoryId":5,"trackId":"D1A453B43D6920A78565E65A4597E353B177ABD0","ghostCount":6324,"ghosts":[{"_links":{"item":{"href":"/rkgd/DB/01/6FD3076C1CB5656DD89BC0667DB9E36AB785.json"},"player":{"href":"/players/70/8BBB3EE59D227F.json"}},"href":"/rkgd/DB/01/6FD3076C1CB5656DD89BC0667DB9E36AB785.rkg","playerId":"708BBB3EE59D227F","finishTime":"00:28.366780926630","finishTimeSimple":"00:28.367","hash":"DB016FD3076C1CB5656DD89BC0667DB9E36AB785","vehicleId":22,"driverId":10,"controller":2,"usbGcnAdapterAttached":false,"player":"INVI>CORE","playersFastest":true,"leaderboardPlayerId":0,"dateSet":"2024-04-26T01:06:34Z","wasWr":true}],"uniquePlayers":2222,"popularity":7,"lastChanged":"2025-09-21T00:52:20Z","fastestTime":"00:28.366780926630","fastestTimeSimple":"00:28.367","fastestTimeLastChange":"2024-04-26T01:06:34Z"}},{"status":"fulfilled","value":{"_links":{"self":{"href":"/leaderboard/09/72D0241C75BE4A5EBD242B9D8D89B1D6FD56BE8F/04.json"},"index":{"href":"/leaderboards.json"},"leaderboardFastLap":{"href":"/leaderboard/09/72D0241C75BE4A5EBD242B9D8D89B1D6FD56BE8F/04-fast-lap.json"}},"name":"Daisy Circuit","authors":["Nintendo"],"slotId":9,"correctSlotId":9,"inCtgp":true,"defaultTrack":true,"200cc":true,"categoryId":4,"trackId":"72D0241C75BE4A5EBD242B9D8D89B1D6FD56BE8F","ghostCount":8000,"ghosts":[{"_links":{"item":{"href":"/rkgd/F9/A0/0FAA6A52AF5593285F447020DA9F3736FE39.json"},"player":{"href":"/players/D3/1D0B090D52771B.json"}},"href":"/rkgd/F9/A0/0FAA6A52AF5593285F447020DA9F3736FE39.rkg","playerId":"D31D0B090D52771B","finishTime":"01:01.573393765807","finishTimeSimple":"01:01.574","hash":"F9A00FAA6A52AF5593285F447020DA9F3736FE39","vehicleId":22,"driverId":15,"controller":2,"usbGcnAdapterAttached":false,"player":"woah","playersFastest":true,"leaderboardPlayerId":0,"dateSet":"2025-01-22T00:23:34Z","wasWr":true}],"uniquePlayers":3966,"popularity":9,"lastChanged":"2025-09-24T09:51:27Z","fastestTime":"01:01.573393765807","fastestTimeSimple":"01:01.574","fastestTimeLastChange":"2025-01-22T00:23:34Z"}},{"status":"fulfilled","value":{"_links":{"self":{"href":"/leaderboard/0F/52F01AE3AED1E0FA4C7459A648494863E83A548C/04.json"},"index":{"href":"/leaderboards.json"},"leaderboardFastLap":{"href":"/leaderboard/0F/52F01AE3AED1E0FA4C7459A648494863E83A548C/04-fast-lap.json"}},"name":"Koopa Cape","authors":["Nintendo"],"slotId":15,"correctSlotId":15,"inCtgp":true,"defaultTrack":true,"200cc":true,"categoryId":4,"trackId":"52F01AE3AED1E0FA4C7459A648494863E83A548C","ghostCount":5424,"ghosts":[{"_links":{"item":{"href":"/rkgd/5D/1B/1B2945277B0070564B774C2D4D7BD8022E03.json"},"player":{"href":"/players/18/75A48ED14ED211.json"}},"href":"/rkgd/5D/1B/1B2945277B0070564B774C2D4D7BD8022E03.rkg","playerId":"1875A48ED14ED211","finishTime":"01:36.877071158290","finishTimeSimple":"01:36.878","hash":"5D1B1B2945277B0070564B774C2D4D7BD8022E03","vehicleId":22,"driverId":15,"controller":2,"usbGcnAdapterAttached":false,"country":110,"region":2,"player":"CobyAltWii","continent":3,"playersFastest":true,"leaderboardPlayerId":0,"dateSet":"2025-01-21T23:08:26Z","wasWr":true}],"uniquePlayers":3119,"popularity":9,"lastChanged":"2025-09-22T03:12:22Z","fastestTime":"01:36.877071158290","fastestTimeSimple":"01:36.878","fastestTimeLastChange":"2025-01-21T23:08:26Z"}},{"status":"fulfilled","value":{"_links":{"self":{"href":"/leaderboard/0F/52F01AE3AED1E0FA4C7459A648494863E83A548C/05.json"},"index":{"href":"/leaderboards.json"},"leaderboardFastLap":{"href":"/leaderboard/0F/52F01AE3AED1E0FA4C7459A648494863E83A548C/05-fast-lap.json"}},"name":"Koopa Cape","authors":["Nintendo"],"slotId":15,"correctSlotId":15,"inCtgp":true,"defaultTrack":true,"200cc":true,"categoryId":5,"trackId":"52F01AE3AED1E0FA4C7459A648494863E83A548C","ghostCount":181,"ghosts":[{"_links":{"item":{"href":"/rkgd/49/F1/F21FCADC7ECD1520BCBF4C007AC6A7C74C4C.json"},"player":{"href":"/players/17/D9E858E51F6859.json"}},"href":"/rkgd/49/F1/F21FCADC7ECD1520BCBF4C007AC6A7C74C4C.rkg","playerId":"17D9E858E51F6859","finishTime":"00:49.630244227469","finishTimeSimple":"00:49.631","hash":"49F1F21FCADC7ECD1520BCBF4C007AC6A7C74C4C","vehicleId":22,"driverId":15,"controller":2,"usbGcnAdapterAttached":false,"country":49,"region":50,"player":"flap","continent":2,"playersFastest":true,"leaderboardPlayerId":0,"dateSet":"2024-04-26T21:14:59Z","wasWr":true}],"uniquePlayers":37,"popularity":0,"lastChanged":"2025-07-15T01:01:26Z","fastestTime":"00:49.630244227469","fastestTimeSimple":"00:49.631","fastestTimeLastChange":"2024-04-26T21:14:59Z"}},{"status":"fulfilled","value":{"_links":{"self":{"href":"/leaderboard/0B/48EBD9D64413C2B98D2B92E5EFC9B15ECD76FEE6/04.json"},"index":{"href":"/leaderboards.json"},"leaderboardFastLap":{"href":"/leaderboard/0B/48EBD9D64413C2B98D2B92E5EFC9B15ECD76FEE6/04-fast-lap.json"}},"name":"Maple Treeway","authors":["Nintendo"],"slotId":11,"correctSlotId":11,"inCtgp":true,"defaultTrack":true,"200cc":true,"categoryId":4,"trackId":"48EBD9D64413C2B98D2B92E5EFC9B15ECD76FEE6","ghostCount":3851,"ghosts":[{"_links":{"item":{"href":"/rkgd/94/BD/9D0DE6BC7A7CBAF120A8F745F6C5A1AE939A.json"},"player":{"href":"/players/D3/1D0B090D52771B.json"}},"href":"/rkgd/94/BD/9D0DE6BC7A7CBAF120A8F745F6C5A1AE939A.rkg","playerId":"D31D0B090D52771B","finishTime":"01:39.931580766857","finishTimeSimple":"01:39.932","hash":"94BD9D0DE6BC7A7CBAF120A8F745F6C5A1AE939A","vehicleId":22,"driverId":15,"controller":2,"usbGcnAdapterAttached":false,"player":"MrWaffle","playersFastest":true,"leaderboardPlayerId":0,"dateSet":"2024-01-19T22:36:53Z","wasWr":true}],"uniquePlayers":2186,"popularity":5,"lastChanged":"2025-09-21T16:25:47Z","fastestTime":"01:39.931580766857","fastestTimeSimple":"01:39.932","fastestTimeLastChange":"2024-01-19T22:36:53Z"}},{"status":"fulfilled","value":{"_links":{"self":{"href":"/leaderboard/0B/48EBD9D64413C2B98D2B92E5EFC9B15ECD76FEE6/05.json"},"index":{"href":"/leaderboards.json"},"leaderboardFastLap":{"href":"/leaderboard/0B/48EBD9D64413C2B98D2B92E5EFC9B15ECD76FEE6/05-fast-lap.json"}},"name":"Maple Treeway","authors":["Nintendo"],"slotId":11,"correctSlotId":11,"inCtgp":true,"defaultTrack":true,"200cc":true,"categoryId":5,"trackId":"48EBD9D64413C2B98D2B92E5EFC9B15ECD76FEE6","ghostCount":333,"ghosts":[{"_links":{"item":{"href":"/rkgd/F8/5F/2F6F750666EC1848668C30B80ACE179ACEBF.json"},"player":{"href":"/players/BA/3BCE569962814B.json"}},"href":"/rkgd/F8/5F/2F6F750666EC1848668C30B80ACE179ACEBF.rkg","playerId":"BA3BCE569962814B","finishTime":"01:05.956787294850","finishTimeSimple":"01:05.957","hash":"F85F2F6F750666EC1848668C30B80ACE179ACEBF","vehicleId":22,"driverId":15,"controller":3,"usbGcnAdapterAttached":false,"country":49,"region":49,"player":"BossBoy28","continent":2,"playersFastest":true,"leaderboardPlayerId":0,"dateSet":"2023-05-14T03:48:53Z","wasWr":true}],"uniquePlayers":112,"popularity":0,"lastChanged":"2025-04-13T01:22:10Z","fastestTime":"01:05.956787294850","fastestTimeSimple":"01:05.957","fastestTimeLastChange":"2023-05-14T03:48:53Z"}},{"status":"fulfilled","value":{"_links":{"self":{"href":"/leaderboard/03/ACC0883AE0CE7879C6EFBA20CFE5B5909BF7841B/04.json"},"index":{"href":"/leaderboards.json"},"leaderboardFastLap":{"href":"/leaderboard/03/ACC0883AE0CE7879C6EFBA20CFE5B5909BF7841B/04-fast-lap.json"}},"name":"Grumble Volcano","authors":["Nintendo"],"slotId":3,"correctSlotId":3,"inCtgp":true,"defaultTrack":true,"200cc":true,"categoryId":4,"trackId":"ACC0883AE0CE7879C6EFBA20CFE5B5909BF7841B","ghostCount":2861,"ghosts":[{"_links":{"item":{"href":"/rkgd/69/9A/58FA9EBB5F7AE028770D792A787B7BE86511.json"},"player":{"href":"/players/D3/1D0B090D52771B.json"}},"href":"/rkgd/69/9A/58FA9EBB5F7AE028770D792A787B7BE86511.rkg","playerId":"D31D0B090D52771B","finishTime":"01:10.741896301918","finishTimeSimple":"01:10.742","hash":"699A58FA9EBB5F7AE028770D792A787B7BE86511","vehicleId":22,"driverId":15,"controller":2,"usbGcnAdapterAttached":false,"player":"woah","playersFastest":true,"leaderboardPlayerId":0,"dateSet":"2023-12-18T14:55:26Z","wasWr":true}],"uniquePlayers":1378,"popularity":5,"lastChanged":"2025-09-22T03:12:24Z","fastestTime":"01:10.741896301918","fastestTimeSimple":"01:10.742","fastestTimeLastChange":"2023-12-18T14:55:26Z"}},{"status":"fulfilled","value":{"_links":{"self":{"href":"/leaderboard/03/ACC0883AE0CE7879C6EFBA20CFE5B5909BF7841B/05.json"},"index":{"href":"/leaderboards.json"},"leaderboardFastLap":{"href":"/leaderboard/03/ACC0883AE0CE7879C6EFBA20CFE5B5909BF7841B/05-fast-lap.json"}},"name":"Grumble Volcano","authors":["Nintendo"],"slotId":3,"correctSlotId":3,"inCtgp":true,"defaultTrack":true,"200cc":true,"categoryId":5,"trackId":"ACC0883AE0CE7879C6EFBA20CFE5B5909BF7841B","ghostCount":7753,"ghosts":[{"_links":{"item":{"href":"/rkgd/F4/48/6834E366F91F5B3ED6B2B08EAE829D358815.json"},"player":{"href":"/players/1E/C3384B8D39B684.json"}},"href":"/rkgd/F4/48/6834E366F91F5B3ED6B2B08EAE829D358815.rkg","playerId":"1EC3384B8D39B684","finishTime":"00:18.980505694926","finishTimeSimple":"00:18.981","hash":"F4486834E366F91F5B3ED6B2B08EAE829D358815","vehicleId":24,"driverId":6,"controller":1,"usbGcnAdapterAttached":false,"country":49,"region":21,"player":"Master☆JCP","continent":2,"playersFastest":true,"leaderboardPlayerId":0,"dateSet":"2022-08-26T00:11:07Z","wasWr":true}],"uniquePlayers":2927,"popularity":6,"lastChanged":"2025-09-18T19:54:41Z","fastestTime":"00:18.980505694926","fastestTimeSimple":"00:18.981","fastestTimeLastChange":"2022-08-26T00:11:07Z"}},{"status":"fulfilled","value":{"_links":{"self":{"href":"/leaderboard/03/ACC0883AE0CE7879C6EFBA20CFE5B5909BF7841B/06.json"},"index":{"href":"/leaderboards.json"},"leaderboardFastLap":{"href":"/leaderboard/03/ACC0883AE0CE7879C6EFBA20CFE5B5909BF7841B/06-fast-lap.json"}},"name":"Grumble Volcano","authors":["Nintendo"],"slotId":3,"correctSlotId":3,"inCtgp":true,"defaultTrack":true,"200cc":true,"categoryId":6,"trackId":"ACC0883AE0CE7879C6EFBA20CFE5B5909BF7841B","ghostCount":2644,"ghosts":[{"_links":{"item":{"href":"/rkgd/E1/A5/13BF968D3BEACE4D32E5D106A28C30453C9F.json"},"player":{"href":"/players/D3/1D0B090D52771B.json"}},"href":"/rkgd/E1/A5/13BF968D3BEACE4D32E5D106A28C30453C9F.rkg","playerId":"D31D0B090D52771B","finishTime":"01:16.891043323577","finishTimeSimple":"01:16.892","hash":"E1A513BF968D3BEACE4D32E5D106A28C30453C9F","vehicleId":22,"driverId":15,"controller":2,"usbGcnAdapterAttached":false,"player":"woah","playersFastest":true,"leaderboardPlayerId":0,"dateSet":"2023-12-30T21:13:12Z","wasWr":true}],"uniquePlayers":1481,"popularity":1,"lastChanged":"2025-09-21T16:25:47Z","fastestTime":"01:16.891043323577","fastestTimeSimple":"01:16.892","fastestTimeLastChange":"2023-12-30T21:13:12Z"}},{"status":"fulfilled","value":{"_links":{"self":{"href":"/leaderboard/0E/38486C4F706395772BD988C1AC5FA30D27CAE098/04.json"},"index":{"href":"/leaderboards.json"},"leaderboardFastLap":{"href":"/leaderboard/0E/38486C4F706395772BD988C1AC5FA30D27CAE098/04-fast-lap.json"}},"name":"Dry Dry Ruins","authors":["Nintendo"],"slotId":14,"correctSlotId":14,"inCtgp":true,"defaultTrack":true,"200cc":true,"trackId":"38486C4F706395772BD988C1AC5FA30D27CAE098","ghostCount":6566,"ghosts":[{"_links":{"item":{"href":"/rkgd/E1/22/ADBBB1031A877DC87AFD2E432E4D5F4DA477.json"},"player":{"href":"/players/D3/1D0B090D52771B.json"}},"href":"/rkgd/E1/22/ADBBB1031A877DC87AFD2E432E4D5F4DA477.rkg","playerId":"D31D0B090D52771B","finishTime":"01:15.241959911287","finishTimeSimple":"01:15.242","hash":"E122ADBBB1031A877DC87AFD2E432E4D5F4DA477","vehicleId":22,"driverId":15,"controller":2,"usbGcnAdapterAttached":false,"player":"MrWaffle","playersFastest":true,"leaderboardPlayerId":0,"dateSet":"2023-07-23T20:54:22Z","wasWr":true}],"uniquePlayers":3219,"popularity":15,"lastChanged":"2025-09-21T01:32:58Z","fastestTime":"01:15.241959911287","fastestTimeSimple":"01:15.242","fastestTimeLastChange":"2023-07-23T20:54:22Z"}},{"status":"fulfilled","value":{"_links":{"self":{"href":"/leaderboard/0A/B13C515475D7DA207DFD5BADD886986147B906FF/04.json"},"index":{"href":"/leaderboards.json"},"leaderboardFastLap":{"href":"/leaderboard/0A/B13C515475D7DA207DFD5BADD886986147B906FF/04-fast-lap.json"}},"name":"Moonview Highway","authors":["Nintendo"],"slotId":10,"correctSlotId":10,"inCtgp":true,"defaultTrack":true,"200cc":true,"categoryId":4,"trackId":"B13C515475D7DA207DFD5BADD886986147B906FF","ghostCount":3423,"ghosts":[{"_links":{"item":{"href":"/rkgd/F7/89/027F83631FB46B29BF2739E455DA92423085.json"},"player":{"href":"/players/D3/1D0B090D52771B.json"}},"href":"/rkgd/F7/89/027F83631FB46B29BF2739E455DA92423085.rkg","playerId":"D31D0B090D52771B","finishTime":"01:09.116484032631","finishTimeSimple":"01:09.117","hash":"F789027F83631FB46B29BF2739E455DA92423085","vehicleId":22,"driverId":15,"controller":2,"usbGcnAdapterAttached":false,"player":"woah","playersFastest":true,"leaderboardPlayerId":0,"dateSet":"2024-11-30T17:11:20Z","wasWr":true}],"uniquePlayers":1888,"popularity":4,"lastChanged":"2025-09-21T09:30:26Z","fastestTime":"01:09.116484032631","fastestTimeSimple":"01:09.117","fastestTimeLastChange":"2024-11-30T17:11:20Z"}},{"status":"fulfilled","value":{"_links":{"self":{"href":"/leaderboard/0C/B9821B14A89381F9C015669353CB24D7DB1BB25D/04.json"},"index":{"href":"/leaderboards.json"},"leaderboardFastLap":{"href":"/leaderboard/0C/B9821B14A89381F9C015669353CB24D7DB1BB25D/04-fast-lap.json"}},"name":"Bowser's Castle","authors":["Nintendo"],"slotId":12,"correctSlotId":12,"inCtgp":true,"defaultTrack":true,"200cc":true,"categoryId":4,"trackId":"B9821B14A89381F9C015669353CB24D7DB1BB25D","ghostCount":794,"ghosts":[{"_links":{"item":{"href":"/rkgd/1D/31/ADC766DB310C4FA25BE133A0D9040EF0C492.json"},"player":{"href":"/players/02/43BB4D89833F9D.json"}},"href":"/rkgd/1D/31/ADC766DB310C4FA25BE133A0D9040EF0C492.rkg","playerId":"0243BB4D89833F9D","finishTime":"01:30.379651095063","finishTimeSimple":"01:30.380","hash":"1D31ADC766DB310C4FA25BE133A0D9040EF0C492","vehicleId":22,"driverId":15,"controller":3,"usbGcnAdapterAttached":true,"country":49,"region":16,"player":"αdcGD@sinθ","continent":2,"playersFastest":true,"leaderboardPlayerId":0,"dateSet":"2025-02-07T06:21:02Z","wasWr":true}],"uniquePlayers":458,"popularity":2,"lastChanged":"2025-08-05T03:41:30Z","fastestTime":"01:30.379651095063","fastestTimeSimple":"01:30.380","fastestTimeLastChange":"2025-02-07T06:21:02Z"}},{"status":"fulfilled","value":{"_links":{"self":{"href":"/leaderboard/0C/B9821B14A89381F9C015669353CB24D7DB1BB25D/05.json"},"index":{"href":"/leaderboards.json"},"leaderboardFastLap":{"href":"/leaderboard/0C/B9821B14A89381F9C015669353CB24D7DB1BB25D/05-fast-lap.json"}},"name":"Bowser's Castle","authors":["Nintendo"],"slotId":12,"correctSlotId":12,"inCtgp":true,"defaultTrack":true,"200cc":true,"categoryId":5,"trackId":"B9821B14A89381F9C015669353CB24D7DB1BB25D","ghostCount":343,"ghosts":[{"_links":{"item":{"href":"/rkgd/76/31/213BF594CCBD43608AEFBE24B94644AD58D3.json"},"player":{"href":"/players/02/43BB4D89833F9D.json"}},"href":"/rkgd/76/31/213BF594CCBD43608AEFBE24B94644AD58D3.rkg","playerId":"0243BB4D89833F9D","finishTime":"01:20.066036076129","finishTimeSimple":"01:20.067","hash":"7631213BF594CCBD43608AEFBE24B94644AD58D3","vehicleId":22,"driverId":15,"controller":3,"usbGcnAdapterAttached":true,"country":49,"region":16,"player":"αdcGD@sinθ","continent":2,"playersFastest":true,"leaderboardPlayerId":0,"dateSet":"2025-01-31T02:25:53Z","wasWr":true}],"uniquePlayers":108,"popularity":1,"lastChanged":"2025-09-20T12:17:40Z","fastestTime":"01:20.066036076129","fastestTimeSimple":"01:20.067","fastestTimeLastChange":"2025-01-31T02:25:53Z"}},{"status":"fulfilled","value":{"_links":{"self":{"href":"/leaderboard/0C/B9821B14A89381F9C015669353CB24D7DB1BB25D/06.json"},"index":{"href":"/leaderboards.json"},"leaderboardFastLap":{"href":"/leaderboard/0C/B9821B14A89381F9C015669353CB24D7DB1BB25D/06-fast-lap.json"}},"name":"Bowser's Castle","authors":["Nintendo"],"slotId":12,"correctSlotId":12,"inCtgp":true,"defaultTrack":true,"200cc":true,"categoryId":6,"trackId":"B9821B14A89381F9C015669353CB24D7DB1BB25D","ghostCount":3055,"ghosts":[{"_links":{"item":{"href":"/rkgd/E0/52/1AA380E8B49DCAB05291214D235A09AC072D.json"},"player":{"href":"/players/D3/1D0B090D52771B.json"}},"href":"/rkgd/E0/52/1AA380E8B49DCAB05291214D235A09AC072D.rkg","playerId":"D31D0B090D52771B","finishTime":"01:40.127125552297","finishTimeSimple":"01:40.128","hash":"E0521AA380E8B49DCAB05291214D235A09AC072D","vehicleId":22,"driverId":15,"controller":2,"usbGcnAdapterAttached":false,"player":"Schmancy","playersFastest":true,"leaderboardPlayerId":0,"dateSet":"2024-04-23T20:59:59Z","wasWr":true}],"uniquePlayers":1741,"popularity":3,"lastChanged":"2025-09-21T09:30:26Z","fastestTime":"01:40.127125552297","fastestTimeSimple":"01:40.128","fastestTimeLastChange":"2024-04-23T20:59:59Z"}},{"status":"fulfilled","value":{"_links":{"self":{"href":"/leaderboard/0D/FFE518915E5FAAA889057C8A3D3E439868574508/04.json"},"index":{"href":"/leaderboards.json"},"leaderboardFastLap":{"href":"/leaderboard/0D/FFE518915E5FAAA889057C8A3D3E439868574508/04-fast-lap.json"}},"name":"Rainbow Road","authors":["Nintendo"],"slotId":13,"correctSlotId":13,"inCtgp":true,"defaultTrack":true,"200cc":true,"categoryId":4,"trackId":"FFE518915E5FAAA889057C8A3D3E439868574508","ghostCount":6297,"ghosts":[{"_links":{"item":{"href":"/rkgd/6F/F8/3890B0E1179F1BAA02CCF977601CFA75D6AB.json"},"player":{"href":"/players/DD/E38FD0B8E94933.json"}},"href":"/rkgd/6F/F8/3890B0E1179F1BAA02CCF977601CFA75D6AB.rkg","playerId":"DDE38FD0B8E94933","finishTime":"01:44.197684081316","finishTimeSimple":"01:44.198","hash":"6FF83890B0E1179F1BAA02CCF977601CFA75D6AB","vehicleId":23,"driverId":22,"controller":1,"usbGcnAdapterAttached":true,"player":"Flαg N","playersFastest":true,"leaderboardPlayerId":0,"dateSet":"2025-09-14T06:27:31Z","wasWr":true}],"uniquePlayers":3378,"popularity":9,"lastChanged":"2025-09-19T15:49:55Z","fastestTime":"01:44.197684081316","fastestTimeSimple":"01:44.198","fastestTimeLastChange":"2025-09-14T06:27:31Z"}},{"status":"fulfilled","value":{"_links":{"self":{"href":"/leaderboard/0D/FFE518915E5FAAA889057C8A3D3E439868574508/05.json"},"index":{"href":"/leaderboards.json"},"leaderboardFastLap":{"href":"/leaderboard/0D/FFE518915E5FAAA889057C8A3D3E439868574508/05-fast-lap.json"}},"name":"Rainbow Road","authors":["Nintendo"],"slotId":13,"correctSlotId":13,"inCtgp":true,"defaultTrack":true,"200cc":true,"categoryId":5,"trackId":"FFE518915E5FAAA889057C8A3D3E439868574508","ghostCount":170,"ghosts":[{"_links":{"item":{"href":"/rkgd/4A/9F/5F781EA26DCB5B7EAC8152BC3760153572AE.json"},"player":{"href":"/players/70/8BBB3EE59D227F.json"}},"href":"/rkgd/4A/9F/5F781EA26DCB5B7EAC8152BC3760153572AE.rkg","playerId":"708BBB3EE59D227F","finishTime":"01:13.060473009288","finishTimeSimple":"01:13.061","hash":"4A9F5F781EA26DCB5B7EAC8152BC3760153572AE","vehicleId":22,"driverId":15,"controller":2,"usbGcnAdapterAttached":false,"player":"Core","playersFastest":true,"leaderboardPlayerId":0,"dateSet":"2025-03-22T22:18:18Z","wasWr":true}],"uniquePlayers":50,"popularity":0,"lastChanged":"2025-08-14T12:04:53Z","fastestTime":"01:13.060473009288","fastestTimeSimple":"01:13.061","fastestTimeLastChange":"2025-03-22T22:18:18Z"}},{"status":"fulfilled","value":{"_links":{"self":{"href":"/leaderboard/10/8014488A60F4428EEF52D01F8C5861CA9565E1CA/04.json"},"index":{"href":"/leaderboards.json"},"leaderboardFastLap":{"href":"/leaderboard/10/8014488A60F4428EEF52D01F8C5861CA9565E1CA/04-fast-lap.json"}},"name":"GCN Peach Beach","authors":["Nintendo"],"slotId":16,"correctSlotId":16,"inCtgp":true,"defaultTrack":true,"200cc":true,"categoryId":4,"trackId":"8014488A60F4428EEF52D01F8C5861CA9565E1CA","ghostCount":11790,"ghosts":[{"_links":{"item":{"href":"/rkgd/DD/EF/24AF634EB2E40AA982F18799881F5EAA7FD8.json"},"player":{"href":"/players/1F/401154EB4C8882.json"}},"href":"/rkgd/DD/EF/24AF634EB2E40AA982F18799881F5EAA7FD8.rkg","playerId":"1F401154EB4C8882","finishTime":"00:48.435427886605","finishTimeSimple":"00:48.436","hash":"DDEF24AF634EB2E40AA982F18799881F5EAA7FD8","vehicleId":23,"driverId":22,"controller":1,"usbGcnAdapterAttached":false,"country":49,"region":14,"player":"Kasey","continent":2,"playersFastest":true,"leaderboardPlayerId":0,"dateSet":"2022-02-13T01:36:07Z","wasWr":true}],"uniquePlayers":4056,"popularity":11,"lastChanged":"2025-09-24T09:51:28Z","fastestTime":"00:48.435427886605","fastestTimeSimple":"00:48.436","fastestTimeLastChange":"2022-02-13T01:36:07Z"}},{"status":"fulfilled","value":{"_links":{"self":{"href":"/leaderboard/10/8014488A60F4428EEF52D01F8C5861CA9565E1CA/05.json"},"index":{"href":"/leaderboards.json"},"leaderboardFastLap":{"href":"/leaderboard/10/8014488A60F4428EEF52D01F8C5861CA9565E1CA/05-fast-lap.json"}},"name":"GCN Peach Beach","authors":["Nintendo"],"slotId":16,"correctSlotId":16,"inCtgp":true,"defaultTrack":true,"200cc":true,"categoryId":5,"trackId":"8014488A60F4428EEF52D01F8C5861CA9565E1CA","ghostCount":132,"ghosts":[{"_links":{"item":{"href":"/rkgd/95/81/D6C6E8C98BDFAAEA8E900F830638534C9695.json"},"player":{"href":"/players/CC/37DD1F13C5ED89.json"}},"href":"/rkgd/95/81/D6C6E8C98BDFAAEA8E900F830638534C9695.rkg","playerId":"CC37DD1F13C5ED89","finishTime":"00:41.580627189219","finishTimeSimple":"00:41.581","hash":"9581D6C6E8C98BDFAAEA8E900F830638534C9695","vehicleId":23,"driverId":22,"controller":1,"usbGcnAdapterAttached":false,"country":18,"region":2,"player":"KingAlεx","continent":2,"playersFastest":true,"leaderboardPlayerId":0,"dateSet":"2024-02-08T04:14:23Z","wasWr":true}],"uniquePlayers":39,"popularity":2,"lastChanged":"2025-09-01T11:49:21Z","fastestTime":"00:41.580627189219","fastestTimeSimple":"00:41.581","fastestTimeLastChange":"2024-02-08T04:14:23Z"}},{"status":"fulfilled","value":{"_links":{"self":{"href":"/leaderboard/14/8C854B087417A92425110CC71E23C944D6997806/04.json"},"index":{"href":"/leaderboards.json"},"leaderboardFastLap":{"href":"/leaderboard/14/8C854B087417A92425110CC71E23C944D6997806/04-fast-lap.json"}},"name":"DS Yoshi Falls","authors":["Nintendo"],"slotId":20,"correctSlotId":20,"inCtgp":true,"defaultTrack":true,"200cc":true,"trackId":"8C854B087417A92425110CC71E23C944D6997806","ghostCount":19201,"ghosts":[{"_links":{"item":{"href":"/rkgd/6C/EC/76DCE78846B26850B831ABADDD205FFDC616.json"},"player":{"href":"/players/D3/1D0B090D52771B.json"}},"href":"/rkgd/6C/EC/76DCE78846B26850B831ABADDD205FFDC616.rkg","playerId":"D31D0B090D52771B","finishTime":"00:38.931280643165","finishTimeSimple":"00:38.932","hash":"6CEC76DCE78846B26850B831ABADDD205FFDC616","vehicleId":23,"driverId":22,"controller":1,"usbGcnAdapterAttached":false,"country":110,"region":2,"player":"HιahowαreU","continent":3,"playersFastest":true,"leaderboardPlayerId":0,"dateSet":"2023-02-09T14:40:57Z","wasWr":true}],"uniquePlayers":6193,"popularity":17,"lastChanged":"2025-09-23T05:27:51Z","fastestTime":"00:38.931280643165","fastestTimeSimple":"00:38.932","fastestTimeLastChange":"2023-02-09T14:40:57Z"}},{"status":"fulfilled","value":{"_links":{"self":{"href":"/leaderboard/19/071D697C4DDB66D3B210F36C7BF878502E79845B/04.json"},"index":{"href":"/leaderboards.json"},"leaderboardFastLap":{"href":"/leaderboard/19/071D697C4DDB66D3B210F36C7BF878502E79845B/04-fast-lap.json"}},"name":"SNES Ghost Valley 2","authors":["Nintendo"],"slotId":25,"correctSlotId":25,"inCtgp":true,"defaultTrack":true,"200cc":true,"categoryId":4,"trackId":"071D697C4DDB66D3B210F36C7BF878502E79845B","ghostCount":12062,"ghosts":[{"_links":{"item":{"href":"/rkgd/4E/47/64CAE8B82456E6E8A612596E768881874F41.json"},"player":{"href":"/players/D3/1D0B090D52771B.json"}},"href":"/rkgd/4E/47/64CAE8B82456E6E8A612596E768881874F41.rkg","playerId":"D31D0B090D52771B","finishTime":"00:35.721654239804","finishTimeSimple":"00:35.722","hash":"4E4764CAE8B82456E6E8A612596E768881874F41","vehicleId":22,"driverId":15,"controller":2,"usbGcnAdapterAttached":false,"player":"Schmaltzy","playersFastest":true,"leaderboardPlayerId":0,"dateSet":"2023-12-07T22:16:00Z","wasWr":true}],"uniquePlayers":4596,"popularity":8,"lastChanged":"2025-09-21T18:24:43Z","fastestTime":"00:35.721654239804","fastestTimeSimple":"00:35.722","fastestTimeLastChange":"2023-12-07T22:16:00Z"}},{"status":"fulfilled","value":{"_links":{"self":{"href":"/leaderboard/19/071D697C4DDB66D3B210F36C7BF878502E79845B/05.json"},"index":{"href":"/leaderboards.json"},"leaderboardFastLap":{"href":"/leaderboard/19/071D697C4DDB66D3B210F36C7BF878502E79845B/05-fast-lap.json"}},"name":"SNES Ghost Valley 2","authors":["Nintendo"],"slotId":25,"correctSlotId":25,"inCtgp":true,"defaultTrack":true,"200cc":true,"categoryId":5,"trackId":"071D697C4DDB66D3B210F36C7BF878502E79845B","ghostCount":178,"ghosts":[{"_links":{"item":{"href":"/rkgd/71/31/601F4DE97296D680BF3618F187E42414BFE7.json"},"player":{"href":"/players/AF/6E4A2BECEDACC9.json"}},"href":"/rkgd/71/31/601F4DE97296D680BF3618F187E42414BFE7.rkg","playerId":"AF6E4A2BECEDACC9","finishTime":"00:36.748783628166","finishTimeSimple":"00:36.749","hash":"7131601F4DE97296D680BF3618F187E42414BFE7","vehicleId":22,"driverId":15,"controller":1,"usbGcnAdapterAttached":false,"player":"Jαcσβ","playersFastest":true,"leaderboardPlayerId":0,"dateSet":"2019-01-13T08:46:13Z","wasWr":true}],"uniquePlayers":95,"popularity":1,"lastChanged":"2025-06-11T20:32:23Z","fastestTime":"00:36.748783628166","fastestTimeSimple":"00:36.749","fastestTimeLastChange":"2019-01-13T08:46:13Z"}},{"status":"fulfilled","value":{"_links":{"self":{"href":"/leaderboard/1A/49514E8F74FEA50E77273C0297086D67E58123E8/04.json"},"index":{"href":"/leaderboards.json"},"leaderboardFastLap":{"href":"/leaderboard/1A/49514E8F74FEA50E77273C0297086D67E58123E8/04-fast-lap.json"}},"name":"N64 Mario Raceway","authors":["Nintendo"],"slotId":26,"correctSlotId":26,"inCtgp":true,"defaultTrack":true,"200cc":true,"trackId":"49514E8F74FEA50E77273C0297086D67E58123E8","ghostCount":14843,"ghosts":[{"_links":{"item":{"href":"/rkgd/3A/99/FBF691FB9B0C1F22BCF7B157B337C4F8E1E8.json"},"player":{"href":"/players/D3/1D0B090D52771B.json"}},"href":"/rkgd/3A/99/FBF691FB9B0C1F22BCF7B157B337C4F8E1E8.rkg","playerId":"D31D0B090D52771B","finishTime":"01:08.802917306967","finishTimeSimple":"01:08.803","hash":"3A99FBF691FB9B0C1F22BCF7B157B337C4F8E1E8","vehicleId":22,"driverId":15,"controller":2,"usbGcnAdapterAttached":false,"player":"woah","playersFastest":true,"leaderboardPlayerId":0,"dateSet":"2024-01-10T17:40:05Z","wasWr":true}],"uniquePlayers":5949,"popularity":19,"lastChanged":"2025-09-22T21:16:27Z","fastestTime":"01:08.802917306967","fastestTimeSimple":"01:08.803","fastestTimeLastChange":"2024-01-10T17:40:05Z"}},{"status":"fulfilled","value":{"_links":{"self":{"href":"/leaderboard/1B/BA9BCFB3731A6CB17DBA219A8D37EA4D52332256/04.json"},"index":{"href":"/leaderboards.json"},"leaderboardFastLap":{"href":"/leaderboard/1B/BA9BCFB3731A6CB17DBA219A8D37EA4D52332256/04-fast-lap.json"}},"name":"N64 Sherbet Land","authors":["Nintendo"],"slotId":27,"correctSlotId":27,"inCtgp":true,"defaultTrack":true,"200cc":true,"categoryId":4,"trackId":"BA9BCFB3731A6CB17DBA219A8D37EA4D52332256","ghostCount":2422,"ghosts":[{"_links":{"item":{"href":"/rkgd/D1/75/9543DB294DD5FEC01873D861B68BADACAB04.json"},"player":{"href":"/players/D3/1D0B090D52771B.json"}},"href":"/rkgd/D1/75/9543DB294DD5FEC01873D861B68BADACAB04.rkg","playerId":"D31D0B090D52771B","finishTime":"01:25.164376416147","finishTimeSimple":"01:25.165","hash":"D1759543DB294DD5FEC01873D861B68BADACAB04","vehicleId":30,"driverId":4,"controller":1,"usbGcnAdapterAttached":false,"player":"Schmancy","playersFastest":true,"leaderboardPlayerId":0,"dateSet":"2023-04-21T17:35:04Z","wasWr":true}],"uniquePlayers":1379,"popularity":5,"lastChanged":"2025-09-22T17:35:00Z","fastestTime":"01:25.164376416147","fastestTimeSimple":"01:25.165","fastestTimeLastChange":"2023-04-21T17:35:04Z"}},{"status":"fulfilled","value":{"_links":{"self":{"href":"/leaderboard/1B/BA9BCFB3731A6CB17DBA219A8D37EA4D52332256/05.json"},"index":{"href":"/leaderboards.json"},"leaderboardFastLap":{"href":"/leaderboard/1B/BA9BCFB3731A6CB17DBA219A8D37EA4D52332256/05-fast-lap.json"}},"name":"N64 Sherbet Land","authors":["Nintendo"],"slotId":27,"correctSlotId":27,"inCtgp":true,"defaultTrack":true,"200cc":true,"categoryId":5,"trackId":"BA9BCFB3731A6CB17DBA219A8D37EA4D52332256","ghostCount":126,"ghosts":[{"_links":{"item":{"href":"/rkgd/33/43/0CE4A4CCEB25CBCC12B89A95F142826A3023.json"},"player":{"href":"/players/65/702F3A15278B49.json"}},"href":"/rkgd/33/43/0CE4A4CCEB25CBCC12B89A95F142826A3023.rkg","playerId":"65702F3A15278B49","finishTime":"00:32.251158163130","finishTimeSimple":"00:32.252","hash":"33430CE4A4CCEB25CBCC12B89A95F142826A3023","vehicleId":30,"driverId":13,"controller":2,"usbGcnAdapterAttached":false,"country":49,"region":50,"player":"flap","continent":2,"playersFastest":true,"leaderboardPlayerId":0,"dateSet":"2023-07-11T00:14:48Z","wasWr":true}],"uniquePlayers":25,"popularity":1,"lastChanged":"2025-08-18T20:27:58Z","fastestTime":"00:32.251158163130","fastestTimeSimple":"00:32.252","fastestTimeLastChange":"2023-07-11T00:14:48Z"}},{"status":"fulfilled","value":{"_links":{"self":{"href":"/leaderboard/1F/E8ED31605CC7D6660691998F024EED6BA8B4A33F/04.json"},"index":{"href":"/leaderboards.json"},"leaderboardFastLap":{"href":"/leaderboard/1F/E8ED31605CC7D6660691998F024EED6BA8B4A33F/04-fast-lap.json"}},"name":"GBA Shy Guy Beach","authors":["Nintendo"],"slotId":31,"correctSlotId":31,"inCtgp":true,"defaultTrack":true,"200cc":true,"categoryId":4,"trackId":"E8ED31605CC7D6660691998F024EED6BA8B4A33F","ghostCount":7053,"ghosts":[{"_links":{"item":{"href":"/rkgd/65/B0/E26080841058093F1B8512BF591EB8C0CAD3.json"},"player":{"href":"/players/D3/1D0B090D52771B.json"}},"href":"/rkgd/65/B0/E26080841058093F1B8512BF591EB8C0CAD3.rkg","playerId":"D31D0B090D52771B","finishTime":"00:54.067415416181","finishTimeSimple":"00:54.068","hash":"65B0E26080841058093F1B8512BF591EB8C0CAD3","vehicleId":30,"driverId":13,"controller":2,"usbGcnAdapterAttached":false,"player":"Schmancy","playersFastest":true,"leaderboardPlayerId":0,"dateSet":"2024-02-19T23:09:13Z","wasWr":true}],"uniquePlayers":2669,"popularity":5,"lastChanged":"2025-09-24T10:26:55Z","fastestTime":"00:54.067415416181","fastestTimeSimple":"00:54.068","fastestTimeLastChange":"2024-02-19T23:09:13Z"}},{"status":"fulfilled","value":{"_links":{"self":{"href":"/leaderboard/1F/E8ED31605CC7D6660691998F024EED6BA8B4A33F/05.json"},"index":{"href":"/leaderboards.json"},"leaderboardFastLap":{"href":"/leaderboard/1F/E8ED31605CC7D6660691998F024EED6BA8B4A33F/05-fast-lap.json"}},"name":"GBA Shy Guy Beach","authors":["Nintendo"],"slotId":31,"correctSlotId":31,"inCtgp":true,"defaultTrack":true,"200cc":true,"categoryId":5,"trackId":"E8ED31605CC7D6660691998F024EED6BA8B4A33F","ghostCount":309,"ghosts":[{"_links":{"item":{"href":"/rkgd/C0/41/EC2EB0DDB9867370663A7C5767D0912E22C6.json"},"player":{"href":"/players/17/D9E858E51F6859.json"}},"href":"/rkgd/C0/41/EC2EB0DDB9867370663A7C5767D0912E22C6.rkg","playerId":"17D9E858E51F6859","finishTime":"00:51.187436624944","finishTimeSimple":"00:51.188","hash":"C041EC2EB0DDB9867370663A7C5767D0912E22C6","vehicleId":34,"driverId":10,"controller":2,"usbGcnAdapterAttached":false,"country":49,"region":50,"player":"flap","continent":2,"playersFastest":true,"leaderboardPlayerId":0,"dateSet":"2025-05-06T19:52:59Z","wasWr":true}],"uniquePlayers":55,"popularity":3,"lastChanged":"2025-09-05T22:43:56Z","fastestTime":"00:51.187436624944","fastestTimeSimple":"00:51.188","fastestTimeLastChange":"2025-05-06T19:52:59Z"}},{"status":"fulfilled","value":{"_links":{"self":{"href":"/leaderboard/17/BC038E163D21D9A1181B60CF90B4D03EFAD9E0C5/04.json"},"index":{"href":"/leaderboards.json"},"leaderboardFastLap":{"href":"/leaderboard/17/BC038E163D21D9A1181B60CF90B4D03EFAD9E0C5/04-fast-lap.json"}},"name":"DS Delfino Square","authors":["Nintendo"],"slotId":23,"correctSlotId":23,"inCtgp":true,"defaultTrack":true,"200cc":true,"trackId":"BC038E163D21D9A1181B60CF90B4D03EFAD9E0C5","ghostCount":6853,"ghosts":[{"_links":{"item":{"href":"/rkgd/8D/67/C94A6EFB75EEF2E3BBF372FAC3D1AC8C6774.json"},"player":{"href":"/players/D3/1D0B090D52771B.json"}},"href":"/rkgd/8D/67/C94A6EFB75EEF2E3BBF372FAC3D1AC8C6774.rkg","playerId":"D31D0B090D52771B","finishTime":"01:22.433160919845","finishTimeSimple":"01:22.434","hash":"8D67C94A6EFB75EEF2E3BBF372FAC3D1AC8C6774","vehicleId":22,"driverId":15,"controller":1,"usbGcnAdapterAttached":false,"country":110,"region":2,"player":"HιahowαreU","continent":3,"playersFastest":true,"leaderboardPlayerId":0,"dateSet":"2023-02-02T20:54:19Z","wasWr":true}],"uniquePlayers":3507,"popularity":4,"lastChanged":"2025-09-24T09:51:29Z","fastestTime":"01:22.433160919845","fastestTimeSimple":"01:22.434","fastestTimeLastChange":"2023-02-02T20:54:19Z"}},{"status":"fulfilled","value":{"_links":{"self":{"href":"/leaderboard/12/418099824AF6BF1CD7F8BB44F61E3A9CC3007DAE/04.json"},"index":{"href":"/leaderboards.json"},"leaderboardFastLap":{"href":"/leaderboard/12/418099824AF6BF1CD7F8BB44F61E3A9CC3007DAE/04-fast-lap.json"}},"name":"GCN Waluigi Stadium","authors":["Nintendo"],"slotId":18,"correctSlotId":18,"inCtgp":true,"defaultTrack":true,"200cc":true,"categoryId":4,"trackId":"418099824AF6BF1CD7F8BB44F61E3A9CC3007DAE","ghostCount":6740,"ghosts":[{"_links":{"item":{"href":"/rkgd/66/9C/920F6FC85379E221D3634CD292F29DA63469.json"},"player":{"href":"/players/D3/1D0B090D52771B.json"}},"href":"/rkgd/66/9C/920F6FC85379E221D3634CD292F29DA63469.rkg","playerId":"D31D0B090D52771B","finishTime":"01:18.753470007539","finishTimeSimple":"01:18.754","hash":"669C920F6FC85379E221D3634CD292F29DA63469","vehicleId":22,"driverId":15,"controller":2,"usbGcnAdapterAttached":false,"player":"woah","playersFastest":true,"leaderboardPlayerId":0,"dateSet":"2024-12-01T22:46:56Z","wasWr":true}],"uniquePlayers":3198,"popularity":10,"lastChanged":"2025-09-24T09:51:29Z","fastestTime":"01:18.753470007539","fastestTimeSimple":"01:18.754","fastestTimeLastChange":"2024-12-01T22:46:56Z"}},{"status":"fulfilled","value":{"_links":{"self":{"href":"/leaderboard/12/418099824AF6BF1CD7F8BB44F61E3A9CC3007DAE/05.json"},"index":{"href":"/leaderboards.json"},"leaderboardFastLap":{"href":"/leaderboard/12/418099824AF6BF1CD7F8BB44F61E3A9CC3007DAE/05-fast-lap.json"}},"name":"GCN Waluigi Stadium","authors":["Nintendo"],"slotId":18,"correctSlotId":18,"inCtgp":true,"defaultTrack":true,"200cc":true,"categoryId":5,"trackId":"418099824AF6BF1CD7F8BB44F61E3A9CC3007DAE","ghostCount":170,"ghosts":[{"_links":{"item":{"href":"/rkgd/67/F7/52A10C4A2BD6A9954819EFBD4280E6D643B2.json"},"player":{"href":"/players/2B/CC7E4F1E811888.json"}},"href":"/rkgd/67/F7/52A10C4A2BD6A9954819EFBD4280E6D643B2.rkg","playerId":"2BCC7E4F1E811888","finishTime":"00:58.153543471873","finishTimeSimple":"00:58.154","hash":"67F752A10C4A2BD6A9954819EFBD4280E6D643B2","vehicleId":22,"driverId":33,"controller":3,"usbGcnAdapterAttached":false,"country":18,"region":10,"player":"Michiru","continent":2,"playersFastest":true,"leaderboardPlayerId":0,"dateSet":"2024-06-14T04:39:59Z","wasWr":true}],"uniquePlayers":47,"popularity":2,"lastChanged":"2025-08-19T16:55:33Z","fastestTime":"00:58.153543471873","fastestTimeSimple":"00:58.154","fastestTimeLastChange":"2024-06-14T04:39:59Z"}},{"status":"fulfilled","value":{"_links":{"self":{"href":"/leaderboard/15/4EC538065FDC8ACF49674300CBDEC5B80CC05A0D/04.json"},"index":{"href":"/leaderboards.json"},"leaderboardFastLap":{"href":"/leaderboard/15/4EC538065FDC8ACF49674300CBDEC5B80CC05A0D/04-fast-lap.json"}},"name":"DS Desert Hills","authors":["Nintendo"],"slotId":21,"correctSlotId":21,"inCtgp":true,"defaultTrack":true,"200cc":true,"categoryId":4,"trackId":"4EC538065FDC8ACF49674300CBDEC5B80CC05A0D","ghostCount":210,"ghosts":[{"_links":{"item":{"href":"/rkgd/51/52/B2ABB450421442B05630E277E629072BE4D8.json"},"player":{"href":"/players/E0/74EE80AE72AC95.json"}},"href":"/rkgd/51/52/B2ABB450421442B05630E277E629072BE4D8.rkg","playerId":"E074EE80AE72AC95","finishTime":"01:08.000308371246","finishTimeSimple":"01:08.001","hash":"5152B2ABB450421442B05630E277E629072BE4D8","vehicleId":22,"driverId":15,"controller":1,"usbGcnAdapterAttached":false,"country":78,"region":11,"player":"τας◎SñοοΡ™","continent":3,"playersFastest":true,"leaderboardPlayerId":0,"dateSet":"2019-05-05T18:11:00Z","wasWr":true}],"uniquePlayers":120,"popularity":1,"lastChanged":"2025-09-05T00:25:11Z","fastestTime":"01:08.000308371246","fastestTimeSimple":"01:08.001","fastestTimeLastChange":"2019-05-05T18:11:00Z"}},{"status":"fulfilled","value":{"_links":{"self":{"href":"/leaderboard/15/4EC538065FDC8ACF49674300CBDEC5B80CC05A0D/06.json"},"index":{"href":"/leaderboards.json"},"leaderboardFastLap":{"href":"/leaderboard/15/4EC538065FDC8ACF49674300CBDEC5B80CC05A0D/06-fast-lap.json"}},"name":"DS Desert Hills","authors":["Nintendo"],"slotId":21,"correctSlotId":21,"inCtgp":true,"defaultTrack":true,"200cc":true,"categoryId":6,"trackId":"4EC538065FDC8ACF49674300CBDEC5B80CC05A0D","ghostCount":5440,"ghosts":[{"_links":{"item":{"href":"/rkgd/33/CE/A03BAEF6DF15E3E1AA4D7C4DA81CADB1E1C5.json"},"player":{"href":"/players/1C/6A832CF6B30CFF.json"}},"href":"/rkgd/33/CE/A03BAEF6DF15E3E1AA4D7C4DA81CADB1E1C5.rkg","playerId":"1C6A832CF6B30CFF","finishTime":"01:03.815364829481","finishTimeSimple":"01:03.816","hash":"33CEA03BAEF6DF15E3E1AA4D7C4DA81CADB1E1C5","vehicleId":23,"driverId":22,"controller":0,"usbGcnAdapterAttached":false,"country":82,"region":3,"player":"ElecTrick","continent":3,"playersFastest":true,"leaderboardPlayerId":0,"dateSet":"2025-09-02T19:51:05Z","wasWr":true}],"uniquePlayers":2514,"popularity":12,"lastChanged":"2025-09-22T02:03:42Z","fastestTime":"01:03.815364829481","fastestTimeSimple":"01:03.816","fastestTimeLastChange":"2025-09-02T19:51:05Z"}},{"status":"fulfilled","value":{"_links":{"self":{"href":"/leaderboard/1E/A4BEA41BE83D816F793F3FAD97D268F71AD99BF9/04.json"},"index":{"href":"/leaderboards.json"},"leaderboardFastLap":{"href":"/leaderboard/1E/A4BEA41BE83D816F793F3FAD97D268F71AD99BF9/04-fast-lap.json"}},"name":"GBA Bowser Castle 3","authors":["Nintendo"],"slotId":30,"correctSlotId":30,"inCtgp":true,"defaultTrack":true,"200cc":true,"categoryId":4,"trackId":"A4BEA41BE83D816F793F3FAD97D268F71AD99BF9","ghostCount":2053,"ghosts":[{"_links":{"item":{"href":"/rkgd/C3/8D/E48405CA66B7E677A055089490E6F1F66B74.json"},"player":{"href":"/players/D3/1D0B090D52771B.json"}},"href":"/rkgd/C3/8D/E48405CA66B7E677A055089490E6F1F66B74.rkg","playerId":"D31D0B090D52771B","finishTime":"01:23.758382639468","finishTimeSimple":"01:23.759","hash":"C38DE48405CA66B7E677A055089490E6F1F66B74","vehicleId":22,"driverId":15,"controller":2,"usbGcnAdapterAttached":false,"player":"woah","playersFastest":true,"leaderboardPlayerId":0,"dateSet":"2024-11-01T00:36:07Z","wasWr":true}],"uniquePlayers":1203,"popularity":4,"lastChanged":"2025-09-19T22:25:44Z","fastestTime":"01:23.758382639468","fastestTimeSimple":"01:23.759","fastestTimeLastChange":"2024-11-01T00:36:07Z"}},{"status":"fulfilled","value":{"_links":{"self":{"href":"/leaderboard/1E/A4BEA41BE83D816F793F3FAD97D268F71AD99BF9/05.json"},"index":{"href":"/leaderboards.json"},"leaderboardFastLap":{"href":"/leaderboard/1E/A4BEA41BE83D816F793F3FAD97D268F71AD99BF9/05-fast-lap.json"}},"name":"GBA Bowser Castle 3","authors":["Nintendo"],"slotId":30,"correctSlotId":30,"inCtgp":true,"defaultTrack":true,"200cc":true,"categoryId":5,"trackId":"A4BEA41BE83D816F793F3FAD97D268F71AD99BF9","ghostCount":6,"ghosts":[{"_links":{"item":{"href":"/rkgd/2E/2E/3BFD18C70ABFC81125B9DECC5E9010C11BF9.json"},"player":{"href":"/players/45/E36FA21029D492.json"}},"href":"/rkgd/2E/2E/3BFD18C70ABFC81125B9DECC5E9010C11BF9.rkg","playerId":"45E36FA21029D492","finishTime":"01:56.977398787737","finishTimeSimple":"01:56.978","hash":"2E2E3BFD18C70ABFC81125B9DECC5E9010C11BF9","vehicleId":22,"driverId":15,"controller":1,"usbGcnAdapterAttached":false,"player":"♪νZσαη☆","playersFastest":true,"leaderboardPlayerId":0,"dateSet":"2024-05-01T18:55:07Z","wasWr":true}],"uniquePlayers":3,"popularity":0,"lastChanged":"2024-05-04T22:58:15Z","fastestTime":"01:56.977398787737","fastestTimeSimple":"01:56.978","fastestTimeLastChange":"2024-05-01T18:55:07Z"}},{"status":"fulfilled","value":{"_links":{"self":{"href":"/leaderboard/1E/A4BEA41BE83D816F793F3FAD97D268F71AD99BF9/06.json"},"index":{"href":"/leaderboards.json"},"leaderboardFastLap":{"href":"/leaderboard/1E/A4BEA41BE83D816F793F3FAD97D268F71AD99BF9/06-fast-lap.json"}},"name":"GBA Bowser Castle 3","authors":["Nintendo"],"slotId":30,"correctSlotId":30,"inCtgp":true,"defaultTrack":true,"200cc":true,"categoryId":6,"trackId":"A4BEA41BE83D816F793F3FAD97D268F71AD99BF9","ghostCount":3858,"ghosts":[{"_links":{"item":{"href":"/rkgd/93/D9/1CA7587611D9833D2EDFB6D1B654E1F4671D.json"},"player":{"href":"/players/D3/1D0B090D52771B.json"}},"href":"/rkgd/93/D9/1CA7587611D9833D2EDFB6D1B654E1F4671D.rkg","playerId":"D31D0B090D52771B","finishTime":"01:32.249752843946","finishTimeSimple":"01:32.250","hash":"93D91CA7587611D9833D2EDFB6D1B654E1F4671D","vehicleId":22,"driverId":15,"controller":2,"usbGcnAdapterAttached":false,"player":"woah","playersFastest":true,"leaderboardPlayerId":0,"dateSet":"2024-10-27T21:36:37Z","wasWr":true}],"uniquePlayers":1978,"popularity":3,"lastChanged":"2025-09-19T19:31:50Z","fastestTime":"01:32.249752843946","fastestTimeSimple":"01:32.250","fastestTimeLastChange":"2024-10-27T21:36:37Z"}},{"status":"fulfilled","value":{"_links":{"self":{"href":"/leaderboard/1D/692D566B05434D8C66A55BDFF486698E0FC96095/04.json"},"index":{"href":"/leaderboards.json"},"leaderboardFastLap":{"href":"/leaderboard/1D/692D566B05434D8C66A55BDFF486698E0FC96095/04-fast-lap.json"}},"name":"N64 DK's Jungle Parkway","authors":["Nintendo"],"slotId":29,"correctSlotId":29,"inCtgp":true,"defaultTrack":true,"200cc":true,"categoryId":4,"trackId":"692D566B05434D8C66A55BDFF486698E0FC96095","ghostCount":513,"ghosts":[{"_links":{"item":{"href":"/rkgd/BC/62/E4778365875FBB054F3A9A4094B824E40F56.json"},"player":{"href":"/players/89/D95A0CF12C9266.json"}},"href":"/rkgd/BC/62/E4778365875FBB054F3A9A4094B824E40F56.rkg","playerId":"89D95A0CF12C9266","finishTime":"01:36.542349202573","finishTimeSimple":"01:36.543","hash":"BC62E4778365875FBB054F3A9A4094B824E40F56","vehicleId":22,"driverId":15,"controller":2,"usbGcnAdapterAttached":false,"country":94,"region":12,"player":"Flαg A","continent":3,"playersFastest":true,"leaderboardPlayerId":0,"dateSet":"2023-12-31T19:47:45Z","wasWr":true}],"uniquePlayers":232,"popularity":0,"lastChanged":"2025-05-15T22:08:39Z","fastestTime":"01:36.542349202573","fastestTimeSimple":"01:36.543","fastestTimeLastChange":"2023-12-31T19:47:45Z"}},{"status":"fulfilled","value":{"_links":{"self":{"href":"/leaderboard/1D/692D566B05434D8C66A55BDFF486698E0FC96095/05.json"},"index":{"href":"/leaderboards.json"},"leaderboardFastLap":{"href":"/leaderboard/1D/692D566B05434D8C66A55BDFF486698E0FC96095/05-fast-lap.json"}},"name":"N64 DK's Jungle Parkway","authors":["Nintendo"],"slotId":29,"correctSlotId":29,"inCtgp":true,"defaultTrack":true,"200cc":true,"categoryId":5,"trackId":"692D566B05434D8C66A55BDFF486698E0FC96095","ghostCount":365,"ghosts":[{"_links":{"item":{"href":"/rkgd/C0/3A/BA10F316BEB5A9071AA8ABD4E7925071DEAF.json"},"player":{"href":"/players/89/D95A0CF12C9266.json"}},"href":"/rkgd/C0/3A/BA10F316BEB5A9071AA8ABD4E7925071DEAF.rkg","playerId":"89D95A0CF12C9266","finishTime":"00:51.276003237605","finishTimeSimple":"00:51.277","hash":"C03ABA10F316BEB5A9071AA8ABD4E7925071DEAF","vehicleId":27,"driverId":4,"controller":2,"usbGcnAdapterAttached":false,"country":94,"region":12,"player":"Flαg A","continent":3,"playersFastest":true,"leaderboardPlayerId":0,"dateSet":"2023-09-06T16:24:59Z","wasWr":true}],"uniquePlayers":92,"popularity":1,"lastChanged":"2025-08-23T17:02:10Z","fastestTime":"00:51.276003237605","fastestTimeSimple":"00:51.277","fastestTimeLastChange":"2023-09-06T16:24:59Z"}},{"status":"fulfilled","value":{"_links":{"self":{"href":"/leaderboard/1D/692D566B05434D8C66A55BDFF486698E0FC96095/06.json"},"index":{"href":"/leaderboards.json"},"leaderboardFastLap":{"href":"/leaderboard/1D/692D566B05434D8C66A55BDFF486698E0FC96095/06-fast-lap.json"}},"name":"N64 DK's Jungle Parkway","authors":["Nintendo"],"slotId":29,"correctSlotId":29,"inCtgp":true,"defaultTrack":true,"200cc":true,"categoryId":6,"trackId":"692D566B05434D8C66A55BDFF486698E0FC96095","ghostCount":2554,"ghosts":[{"_links":{"item":{"href":"/rkgd/0B/FD/4630BE11A066AA7E07E5FDDFAFCAB888C605.json"},"player":{"href":"/players/D3/1D0B090D52771B.json"}},"href":"/rkgd/0B/FD/4630BE11A066AA7E07E5FDDFAFCAB888C605.rkg","playerId":"D31D0B090D52771B","finishTime":"01:38.786955121037","finishTimeSimple":"01:38.787","hash":"0BFD4630BE11A066AA7E07E5FDDFAFCAB888C605","vehicleId":22,"driverId":15,"controller":2,"usbGcnAdapterAttached":false,"player":"woah","playersFastest":true,"leaderboardPlayerId":0,"dateSet":"2025-01-24T21:15:02Z","wasWr":true}],"uniquePlayers":1240,"popularity":2,"lastChanged":"2025-09-21T09:05:35Z","fastestTime":"01:38.786955121037","fastestTimeSimple":"01:38.787","fastestTimeLastChange":"2025-01-24T21:15:02Z"}},{"status":"fulfilled","value":{"_links":{"self":{"href":"/leaderboard/11/1941A29AD2E7B7BBA8A29E6440C95EF5CF76B01D/05.json"},"index":{"href":"/leaderboards.json"},"leaderboardFastLap":{"href":"/leaderboard/11/1941A29AD2E7B7BBA8A29E6440C95EF5CF76B01D/05-fast-lap.json"}},"name":"GCN Mario Circuit","authors":["Nintendo"],"slotId":17,"correctSlotId":17,"inCtgp":true,"defaultTrack":true,"200cc":true,"categoryId":5,"trackId":"1941A29AD2E7B7BBA8A29E6440C95EF5CF76B01D","ghostCount":27,"ghosts":[{"_links":{"item":{"href":"/rkgd/C2/D8/14AD44FB5F352E00252AF9D1919C218BCB90.json"},"player":{"href":"/players/1D/395C1266BE577C.json"}},"href":"/rkgd/C2/D8/14AD44FB5F352E00252AF9D1919C218BCB90.rkg","playerId":"1D395C1266BE577C","finishTime":"01:10.662660015225","finishTimeSimple":"01:10.663","hash":"C2D814AD44FB5F352E00252AF9D1919C218BCB90","vehicleId":23,"driverId":22,"controller":1,"usbGcnAdapterAttached":false,"player":"««Aηdrεω»»","playersFastest":true,"leaderboardPlayerId":0,"dateSet":"2025-05-11T23:52:07Z","wasWr":true}],"uniquePlayers":14,"popularity":1,"lastChanged":"2025-09-15T21:59:29Z","fastestTime":"01:10.662660015225","fastestTimeSimple":"01:10.663","fastestTimeLastChange":"2025-05-11T23:52:07Z"}},{"status":"fulfilled","value":{"_links":{"self":{"href":"/leaderboard/11/1941A29AD2E7B7BBA8A29E6440C95EF5CF76B01D/06.json"},"index":{"href":"/leaderboards.json"},"leaderboardFastLap":{"href":"/leaderboard/11/1941A29AD2E7B7BBA8A29E6440C95EF5CF76B01D/06-fast-lap.json"}},"name":"GCN Mario Circuit","authors":["Nintendo"],"slotId":17,"correctSlotId":17,"inCtgp":true,"defaultTrack":true,"200cc":true,"categoryId":6,"trackId":"1941A29AD2E7B7BBA8A29E6440C95EF5CF76B01D","ghostCount":3325,"ghosts":[{"_links":{"item":{"href":"/rkgd/D5/17/C5CF1B956C67B4338E9AD7A5162913AAA36F.json"},"player":{"href":"/players/D3/1D0B090D52771B.json"}},"href":"/rkgd/D5/17/C5CF1B956C67B4338E9AD7A5162913AAA36F.rkg","playerId":"D31D0B090D52771B","finishTime":"01:04.459483247340","finishTimeSimple":"01:04.460","hash":"D517C5CF1B956C67B4338E9AD7A5162913AAA36F","vehicleId":22,"driverId":15,"controller":2,"usbGcnAdapterAttached":false,"player":"woah","playersFastest":true,"leaderboardPlayerId":0,"dateSet":"2024-11-30T17:11:19Z","wasWr":true}],"uniquePlayers":1785,"popularity":3,"lastChanged":"2025-09-22T03:12:27Z","fastestTime":"01:04.459483247340","fastestTimeSimple":"01:04.460","fastestTimeLastChange":"2024-11-30T17:11:19Z"}},{"status":"fulfilled","value":{"_links":{"self":{"href":"/leaderboard/18/077111B996E5C4F47D20EC29C2938504B53A8E76/04.json"},"index":{"href":"/leaderboards.json"},"leaderboardFastLap":{"href":"/leaderboard/18/077111B996E5C4F47D20EC29C2938504B53A8E76/04-fast-lap.json"}},"name":"SNES Mario Circuit 3","authors":["Nintendo"],"slotId":24,"correctSlotId":24,"inCtgp":true,"defaultTrack":true,"200cc":true,"categoryId":4,"trackId":"077111B996E5C4F47D20EC29C2938504B53A8E76","ghostCount":9121,"ghosts":[{"_links":{"item":{"href":"/rkgd/2C/17/0F0B13FC08A2334DB24C140B0E0C32BE55A1.json"},"player":{"href":"/players/D3/1D0B090D52771B.json"}},"href":"/rkgd/2C/17/0F0B13FC08A2334DB24C140B0E0C32BE55A1.rkg","playerId":"D31D0B090D52771B","finishTime":"00:54.326374278665","finishTimeSimple":"00:54.327","hash":"2C170F0B13FC08A2334DB24C140B0E0C32BE55A1","vehicleId":22,"driverId":15,"controller":2,"usbGcnAdapterAttached":false,"player":"woah","playersFastest":true,"leaderboardPlayerId":0,"dateSet":"2024-11-16T00:33:53Z","wasWr":true}],"uniquePlayers":3434,"popularity":14,"lastChanged":"2025-09-13T09:19:06Z","fastestTime":"00:54.326374278665","fastestTimeSimple":"00:54.327","fastestTimeLastChange":"2024-11-16T00:33:53Z"}},{"status":"fulfilled","value":{"_links":{"self":{"href":"/leaderboard/16/F9A62BEF04CC8F499633E4023ACC7675A92771F0/04.json"},"index":{"href":"/leaderboards.json"},"leaderboardFastLap":{"href":"/leaderboard/16/F9A62BEF04CC8F499633E4023ACC7675A92771F0/04-fast-lap.json"}},"name":"DS Peach Gardens","authors":["Nintendo"],"slotId":22,"correctSlotId":22,"inCtgp":true,"defaultTrack":true,"200cc":true,"categoryId":4,"trackId":"F9A62BEF04CC8F499633E4023ACC7675A92771F0","ghostCount":2660,"ghosts":[{"_links":{"item":{"href":"/rkgd/15/A2/F824F16CD1F24A30A69633102AF328485CBB.json"},"player":{"href":"/players/D3/1D0B090D52771B.json"}},"href":"/rkgd/15/A2/F824F16CD1F24A30A69633102AF328485CBB.rkg","playerId":"D31D0B090D52771B","finishTime":"01:21.626528257221","finishTimeSimple":"01:21.627","hash":"15A2F824F16CD1F24A30A69633102AF328485CBB","vehicleId":23,"driverId":22,"controller":1,"usbGcnAdapterAttached":false,"player":"Schmancy","playersFastest":true,"leaderboardPlayerId":0,"dateSet":"2023-03-25T22:48:42Z","wasWr":true}],"uniquePlayers":1480,"popularity":3,"lastChanged":"2025-09-20T18:51:58Z","fastestTime":"01:21.626528257221","fastestTimeSimple":"01:21.627","fastestTimeLastChange":"2023-03-25T22:48:42Z"}},{"status":"fulfilled","value":{"_links":{"self":{"href":"/leaderboard/16/F9A62BEF04CC8F499633E4023ACC7675A92771F0/05.json"},"index":{"href":"/leaderboards.json"},"leaderboardFastLap":{"href":"/leaderboard/16/F9A62BEF04CC8F499633E4023ACC7675A92771F0/05-fast-lap.json"}},"name":"DS Peach Gardens","authors":["Nintendo"],"slotId":22,"correctSlotId":22,"inCtgp":true,"defaultTrack":true,"200cc":true,"categoryId":5,"trackId":"F9A62BEF04CC8F499633E4023ACC7675A92771F0","ghostCount":36,"ghosts":[{"_links":{"item":{"href":"/rkgd/51/30/535C5467903388272A46077B3117409381B3.json"},"player":{"href":"/players/70/8BBB3EE59D227F.json"}},"href":"/rkgd/51/30/535C5467903388272A46077B3117409381B3.rkg","playerId":"708BBB3EE59D227F","finishTime":"01:20.247786376983","finishTimeSimple":"01:20.248","hash":"5130535C5467903388272A46077B3117409381B3","vehicleId":22,"driverId":15,"controller":2,"usbGcnAdapterAttached":false,"player":"Ogg Vorbis","playersFastest":true,"leaderboardPlayerId":0,"dateSet":"2025-08-04T22:46:48Z","wasWr":true}],"uniquePlayers":8,"popularity":3,"lastChanged":"2025-08-30T14:11:12Z","fastestTime":"01:20.247786376983","fastestTimeSimple":"01:20.248","fastestTimeLastChange":"2025-08-04T22:46:48Z"}},{"status":"fulfilled","value":{"_links":{"self":{"href":"/leaderboard/13/B036864CF0016BE0581449EF29FB52B2E58D78A4/04.json"},"index":{"href":"/leaderboards.json"},"leaderboardFastLap":{"href":"/leaderboard/13/B036864CF0016BE0581449EF29FB52B2E58D78A4/04-fast-lap.json"}},"name":"GCN DK Mountain","authors":["Nintendo"],"slotId":19,"correctSlotId":19,"inCtgp":true,"defaultTrack":true,"200cc":true,"categoryId":4,"trackId":"B036864CF0016BE0581449EF29FB52B2E58D78A4","ghostCount":213,"ghosts":[{"_links":{"item":{"href":"/rkgd/9C/8D/0306872D122B9923AE84D439C6BF64089454.json"},"player":{"href":"/players/7E/B2C558D30BFE32.json"}},"href":"/rkgd/9C/8D/0306872D122B9923AE84D439C6BF64089454.rkg","playerId":"7EB2C558D30BFE32","finishTime":"01:36.583504055888","finishTimeSimple":"01:36.584","hash":"9C8D0306872D122B9923AE84D439C6BF64089454","vehicleId":22,"driverId":15,"controller":2,"usbGcnAdapterAttached":false,"country":136,"region":2,"player":"Mγsτοgαη","continent":5,"playersFastest":true,"leaderboardPlayerId":0,"dateSet":"2024-01-24T02:35:15Z","wasWr":true}],"uniquePlayers":119,"popularity":1,"lastChanged":"2025-07-26T18:04:21Z","fastestTime":"01:36.583504055888","fastestTimeSimple":"01:36.584","fastestTimeLastChange":"2024-01-24T02:35:15Z"}},{"status":"fulfilled","value":{"_links":{"self":{"href":"/leaderboard/13/B036864CF0016BE0581449EF29FB52B2E58D78A4/06.json"},"index":{"href":"/leaderboards.json"},"leaderboardFastLap":{"href":"/leaderboard/13/B036864CF0016BE0581449EF29FB52B2E58D78A4/06-fast-lap.json"}},"name":"GCN DK Mountain","authors":["Nintendo"],"slotId":19,"correctSlotId":19,"inCtgp":true,"defaultTrack":true,"200cc":true,"categoryId":6,"trackId":"B036864CF0016BE0581449EF29FB52B2E58D78A4","ghostCount":4152,"ghosts":[{"_links":{"item":{"href":"/rkgd/67/19/4202DFA36B7EC5800A0DA39FF6A464CB5052.json"},"player":{"href":"/players/CC/37DD1F13C5ED89.json"}},"href":"/rkgd/67/19/4202DFA36B7EC5800A0DA39FF6A464CB5052.rkg","playerId":"CC37DD1F13C5ED89","finishTime":"01:38.095287221968","finishTimeSimple":"01:38.096","hash":"67194202DFA36B7EC5800A0DA39FF6A464CB5052","vehicleId":22,"driverId":15,"controller":1,"usbGcnAdapterAttached":false,"country":18,"region":2,"player":"KingAlεx","continent":2,"playersFastest":true,"leaderboardPlayerId":0,"dateSet":"2022-02-10T03:58:34Z","wasWr":true}],"uniquePlayers":2216,"popularity":8,"lastChanged":"2025-09-20T06:36:13Z","fastestTime":"01:38.095287221968","fastestTimeSimple":"01:38.096","fastestTimeLastChange":"2022-02-10T03:58:34Z"}},{"status":"fulfilled","value":{"_links":{"self":{"href":"/leaderboard/1C/15B303B288F4707E5D0AF28367C8CE51CDEAB490/04.json"},"index":{"href":"/leaderboards.json"},"leaderboardFastLap":{"href":"/leaderboard/1C/15B303B288F4707E5D0AF28367C8CE51CDEAB490/04-fast-lap.json"}},"name":"N64 Bowser's Castle","authors":["Nintendo"],"slotId":28,"correctSlotId":28,"inCtgp":true,"defaultTrack":true,"200cc":true,"categoryId":4,"trackId":"15B303B288F4707E5D0AF28367C8CE51CDEAB490","ghostCount":64,"ghosts":[{"_links":{"item":{"href":"/rkgd/B8/91/9B3784217B41619DFB3A69EDAB081FEC12F0.json"},"player":{"href":"/players/0E/611CC121B8C1B9.json"}},"href":"/rkgd/B8/91/9B3784217B41619DFB3A69EDAB081FEC12F0.rkg","playerId":"0E611CC121B8C1B9","finishTime":"01:51.313251447082","finishTimeSimple":"01:51.314","hash":"B8919B3784217B41619DFB3A69EDAB081FEC12F0","vehicleId":22,"driverId":15,"controller":0,"usbGcnAdapterAttached":false,"country":105,"region":12,"player":"Sergio ","continent":3,"playersFastest":true,"leaderboardPlayerId":0,"dateSet":"2022-12-29T14:53:16Z","wasWr":true}],"uniquePlayers":17,"popularity":1,"lastChanged":"2025-01-10T22:01:14Z","fastestTime":"01:51.313251447082","fastestTimeSimple":"01:51.314","fastestTimeLastChange":"2022-12-29T14:53:16Z"}},{"status":"fulfilled","value":{"_links":{"self":{"href":"/leaderboard/1C/15B303B288F4707E5D0AF28367C8CE51CDEAB490/05.json"},"index":{"href":"/leaderboards.json"},"leaderboardFastLap":{"href":"/leaderboard/1C/15B303B288F4707E5D0AF28367C8CE51CDEAB490/05-fast-lap.json"}},"name":"N64 Bowser's Castle","authors":["Nintendo"],"slotId":28,"correctSlotId":28,"inCtgp":true,"defaultTrack":true,"200cc":true,"categoryId":5,"trackId":"15B303B288F4707E5D0AF28367C8CE51CDEAB490","ghostCount":91,"ghosts":[{"_links":{"item":{"href":"/rkgd/76/10/D45EF7F29D1FB2C5FFAAE799B4FCFC12AA11.json"},"player":{"href":"/players/D3/1D0B090D52771B.json"}},"href":"/rkgd/76/10/D45EF7F29D1FB2C5FFAAE799B4FCFC12AA11.rkg","playerId":"D31D0B090D52771B","finishTime":"01:33.460511438727","finishTimeSimple":"01:33.461","hash":"7610D45EF7F29D1FB2C5FFAAE799B4FCFC12AA11","vehicleId":22,"driverId":15,"controller":2,"usbGcnAdapterAttached":false,"player":"Schmancy","playersFastest":true,"leaderboardPlayerId":0,"dateSet":"2023-06-24T19:05:14Z","wasWr":true}],"uniquePlayers":31,"popularity":2,"lastChanged":"2025-09-22T10:56:01Z","fastestTime":"01:33.460511438727","fastestTimeSimple":"01:33.461","fastestTimeLastChange":"2023-06-24T19:05:14Z"}},{"status":"fulfilled","value":{"_links":{"self":{"href":"/leaderboard/1C/15B303B288F4707E5D0AF28367C8CE51CDEAB490/06.json"},"index":{"href":"/leaderboards.json"},"leaderboardFastLap":{"href":"/leaderboard/1C/15B303B288F4707E5D0AF28367C8CE51CDEAB490/06-fast-lap.json"}},"name":"N64 Bowser's Castle","authors":["Nintendo"],"slotId":28,"correctSlotId":28,"inCtgp":true,"defaultTrack":true,"200cc":true,"categoryId":6,"trackId":"15B303B288F4707E5D0AF28367C8CE51CDEAB490","ghostCount":5918,"ghosts":[{"_links":{"item":{"href":"/rkgd/F5/CD/78CBD52706D11E9BCEAB97809880DE26DEC4.json"},"player":{"href":"/players/D3/1D0B090D52771B.json"}},"href":"/rkgd/F5/CD/78CBD52706D11E9BCEAB97809880DE26DEC4.rkg","playerId":"D31D0B090D52771B","finishTime":"01:44.958843354330","finishTimeSimple":"01:44.959","hash":"F5CD78CBD52706D11E9BCEAB97809880DE26DEC4","vehicleId":22,"driverId":15,"controller":2,"usbGcnAdapterAttached":false,"player":"woah","playersFastest":true,"leaderboardPlayerId":0,"dateSet":"2024-12-12T22:48:44Z","wasWr":true}],"uniquePlayers":3110,"popularity":6,"lastChanged":"2025-09-22T21:24:01Z","fastestTime":"01:44.958843354330","fastestTimeSimple":"01:44.959","fastestTimeLastChange":"2024-12-12T22:48:44Z"}}]